[
  {
    "id" : "IHE.mCSD.DataSource",
    "type" : "CapabilityStatement",
    "url" : "https://profiles.ihe.net/ITI/mCSD/CapabilityStatement/IHE.mCSD.DataSource",
    "version" : "4.0.0-comment",
    "name" : "IHE_mCSD_Data_Source"
  },
  {
    "id" : "IHE.mCSD.Directory",
    "type" : "CapabilityStatement",
    "url" : "https://profiles.ihe.net/ITI/mCSD/CapabilityStatement/IHE.mCSD.Directory",
    "version" : "4.0.0-comment",
    "name" : "IHE_mCSD_Directory"
  },
  {
    "id" : "IHE.mCSD.Directory.Feed",
    "type" : "CapabilityStatement",
    "url" : "https://profiles.ihe.net/ITI/mCSD/CapabilityStatement/IHE.mCSD.Directory.Feed",
    "version" : "4.0.0-comment",
    "name" : "IHE_mCSD_Directory_Feed"
  },
  {
    "id" : "IHE.mCSD.Directory.LocationDistance",
    "type" : "CapabilityStatement",
    "url" : "https://profiles.ihe.net/ITI/mCSD/CapabilityStatement/IHE.mCSD.Directory.LocationDistance",
    "version" : "4.0.0-comment",
    "name" : "IHE_mCSD_Directory_Location_Distance_Option"
  },
  {
    "id" : "IHE.mCSD.Directory.Update",
    "type" : "CapabilityStatement",
    "url" : "https://profiles.ihe.net/ITI/mCSD/CapabilityStatement/IHE.mCSD.Directory.Update",
    "version" : "4.0.0-comment",
    "name" : "IHE_mCSD_Directory_Update"
  },
  {
    "id" : "IHE.mCSD.QueryClient",
    "type" : "CapabilityStatement",
    "url" : "https://profiles.ihe.net/ITI/mCSD/CapabilityStatement/IHE.mCSD.QueryClient",
    "version" : "4.0.0-comment",
    "name" : "IHE_mCSD_Query_Client"
  },
  {
    "id" : "IHE.mCSD.QueryClient.LocationDistance",
    "type" : "CapabilityStatement",
    "url" : "https://profiles.ihe.net/ITI/mCSD/CapabilityStatement/IHE.mCSD.QueryClient.LocationDistance",
    "version" : "4.0.0-comment",
    "name" : "IHE_mCSD_Query_Client_Location_Distance_Option"
  },
  {
    "id" : "IHE.mCSD.UpdateClient",
    "type" : "CapabilityStatement",
    "url" : "https://profiles.ihe.net/ITI/mCSD/CapabilityStatement/IHE.mCSD.UpdateClient",
    "version" : "4.0.0-comment",
    "name" : "IHE_mCSD_Update_Client"
  },
  {
    "id" : "IHE.mCSD.Organization.Location.Types",
    "type" : "CodeSystem",
    "url" : "https://profiles.ihe.net/ITI/mCSD/CodeSystem/IHE.mCSD.Organization.Location.Types",
    "version" : "4.0.0-comment",
    "name" : "MCSDOrganizationLocationTypes"
  },
  {
    "id" : "MCSDEndpointIdentifierTypes",
    "type" : "CodeSystem",
    "url" : "https://profiles.ihe.net/ITI/mCSD/CodeSystem/MCSDEndpointIdentifierTypes",
    "version" : "4.0.0-comment",
    "name" : "MCSDEndpointIdentifierTypes"
  },
  {
    "id" : "MCSDEndpointTypes",
    "type" : "CodeSystem",
    "url" : "https://profiles.ihe.net/ITI/mCSD/CodeSystem/MCSDEndpointTypes",
    "version" : "4.0.0-comment",
    "name" : "MCSDEndpointTypes"
  },
  {
    "id" : "MCSDOrgAffTypes",
    "type" : "CodeSystem",
    "url" : "https://profiles.ihe.net/ITI/mCSD/CodeSystem/MCSDOrgAffTypes",
    "version" : "4.0.0-comment",
    "name" : "MCSDOrgAffTypes"
  },
  {
    "id" : "MCSDOrganizationIdentifierTypes",
    "type" : "CodeSystem",
    "url" : "https://profiles.ihe.net/ITI/mCSD/CodeSystem/MCSDOrganizationIdentifierTypes",
    "version" : "4.0.0-comment",
    "name" : "MCSDOrganizationIdentifierTypes"
  },
  {
    "id" : "mcsd-example-hierarchy",
    "type" : "CodeSystem",
    "url" : "https://profiles.ihe.net/ITI/mCSD/CodeSystem/mcsd-example-hierarchy",
    "version" : "4.0.0-comment",
    "name" : "MCSDExampleHierarchy"
  },
  {
    "id" : "ihe.iti.mcsd",
    "type" : "ImplementationGuide",
    "url" : "https://profiles.ihe.net/ITI/mCSD/ImplementationGuide/ihe.iti.mcsd",
    "version" : "4.0.0-comment",
    "name" : "IHE_ITI_mCSD"
  },
  {
    "id" : "Endpoint-EndpointSpecificType",
    "type" : "SearchParameter",
    "url" : "https://profiles.ihe.net/ITI/mCSD/SearchParameter/Endpoint-EndpointSpecificType",
    "version" : "4.0.0-comment",
    "name" : "EndpointSpecificType"
  },
  {
    "id" : "IHE.mCSD.Search.PurposeOfUse",
    "type" : "SearchParameter",
    "url" : "https://profiles.ihe.net/ITI/mCSD/SearchParameter/IHE.mCSD.Search.PurposeOfUse",
    "version" : "4.0.0-comment",
    "name" : "IHE_mCSD_Search_PurposeOfUse"
  },
  {
    "id" : "IHE.mCSD.Audit.CareServices.Create",
    "type" : "StructureDefinition",
    "url" : "https://profiles.ihe.net/ITI/mCSD/StructureDefinition/IHE.mCSD.Audit.CareServices.Create",
    "version" : "4.0.0-comment",
    "name" : "AuditMcsdCareServicesCreate"
  },
  {
    "id" : "IHE.mCSD.Audit.CareServices.Delete",
    "type" : "StructureDefinition",
    "url" : "https://profiles.ihe.net/ITI/mCSD/StructureDefinition/IHE.mCSD.Audit.CareServices.Delete",
    "version" : "4.0.0-comment",
    "name" : "AuditMcsdCareServicesDelete"
  },
  {
    "id" : "IHE.mCSD.Audit.CareServices.Process",
    "type" : "StructureDefinition",
    "url" : "https://profiles.ihe.net/ITI/mCSD/StructureDefinition/IHE.mCSD.Audit.CareServices.Process",
    "version" : "4.0.0-comment",
    "name" : "AuditMcsdCareServicesProcess"
  },
  {
    "id" : "IHE.mCSD.Audit.CareServices.Query",
    "type" : "StructureDefinition",
    "url" : "https://profiles.ihe.net/ITI/mCSD/StructureDefinition/IHE.mCSD.Audit.CareServices.Query",
    "version" : "4.0.0-comment",
    "name" : "AuditMcsdCareServicesQuery"
  },
  {
    "id" : "IHE.mCSD.Audit.CareServices.Read",
    "type" : "StructureDefinition",
    "url" : "https://profiles.ihe.net/ITI/mCSD/StructureDefinition/IHE.mCSD.Audit.CareServices.Read",
    "version" : "4.0.0-comment",
    "name" : "AuditMcsdCareServicesRead"
  },
  {
    "id" : "IHE.mCSD.Audit.CareServices.Update",
    "type" : "StructureDefinition",
    "url" : "https://profiles.ihe.net/ITI/mCSD/StructureDefinition/IHE.mCSD.Audit.CareServices.Update",
    "version" : "4.0.0-comment",
    "name" : "AuditMcsdCareServicesUpdate"
  },
  {
    "id" : "IHE.mCSD.Audit.CareServices.Updates",
    "type" : "StructureDefinition",
    "url" : "https://profiles.ihe.net/ITI/mCSD/StructureDefinition/IHE.mCSD.Audit.CareServices.Updates",
    "version" : "4.0.0-comment",
    "name" : "AuditMcsdCareServicesUpdates"
  },
  {
    "id" : "IHE.mCSD.Endpoint",
    "type" : "StructureDefinition",
    "url" : "https://profiles.ihe.net/ITI/mCSD/StructureDefinition/IHE.mCSD.Endpoint",
    "version" : "4.0.0-comment",
    "name" : "MCSDEndpoint"
  },
  {
    "id" : "IHE.mCSD.Endpoint.DocShare",
    "type" : "StructureDefinition",
    "url" : "https://profiles.ihe.net/ITI/mCSD/StructureDefinition/IHE.mCSD.Endpoint.DocShare",
    "version" : "4.0.0-comment",
    "name" : "MCSDEndpointDocShare"
  },
  {
    "id" : "IHE.mCSD.FacilityLocation",
    "type" : "StructureDefinition",
    "url" : "https://profiles.ihe.net/ITI/mCSD/StructureDefinition/IHE.mCSD.FacilityLocation",
    "version" : "4.0.0-comment",
    "name" : "MCSDFacilityLocation"
  },
  {
    "id" : "IHE.mCSD.FacilityOrganization",
    "type" : "StructureDefinition",
    "url" : "https://profiles.ihe.net/ITI/mCSD/StructureDefinition/IHE.mCSD.FacilityOrganization",
    "version" : "4.0.0-comment",
    "name" : "MCSDFacilityOrganization"
  },
  {
    "id" : "IHE.mCSD.HealthcareService",
    "type" : "StructureDefinition",
    "url" : "https://profiles.ihe.net/ITI/mCSD/StructureDefinition/IHE.mCSD.HealthcareService",
    "version" : "4.0.0-comment",
    "name" : "MCSDHealthcareService"
  },
  {
    "id" : "IHE.mCSD.JurisdictionLocation",
    "type" : "StructureDefinition",
    "url" : "https://profiles.ihe.net/ITI/mCSD/StructureDefinition/IHE.mCSD.JurisdictionLocation",
    "version" : "4.0.0-comment",
    "name" : "MCSDJurisdictionLocation"
  },
  {
    "id" : "IHE.mCSD.JurisdictionOrganization",
    "type" : "StructureDefinition",
    "url" : "https://profiles.ihe.net/ITI/mCSD/StructureDefinition/IHE.mCSD.JurisdictionOrganization",
    "version" : "4.0.0-comment",
    "name" : "MCSDJurisdictionOrganization"
  },
  {
    "id" : "IHE.mCSD.Location",
    "type" : "StructureDefinition",
    "url" : "https://profiles.ihe.net/ITI/mCSD/StructureDefinition/IHE.mCSD.Location",
    "version" : "4.0.0-comment",
    "name" : "MCSDLocation"
  },
  {
    "id" : "IHE.mCSD.LocationDistance",
    "type" : "StructureDefinition",
    "url" : "https://profiles.ihe.net/ITI/mCSD/StructureDefinition/IHE.mCSD.LocationDistance",
    "version" : "4.0.0-comment",
    "name" : "MCSDLocationDistance"
  },
  {
    "id" : "IHE.mCSD.Organization",
    "type" : "StructureDefinition",
    "url" : "https://profiles.ihe.net/ITI/mCSD/StructureDefinition/IHE.mCSD.Organization",
    "version" : "4.0.0-comment",
    "name" : "MCSDOrganization"
  },
  {
    "id" : "IHE.mCSD.OrganizationAffiliation",
    "type" : "StructureDefinition",
    "url" : "https://profiles.ihe.net/ITI/mCSD/StructureDefinition/IHE.mCSD.OrganizationAffiliation",
    "version" : "4.0.0-comment",
    "name" : "MCSDOrganizationAffiliation"
  },
  {
    "id" : "IHE.mCSD.OrganizationAffiliation.DocShare",
    "type" : "StructureDefinition",
    "url" : "https://profiles.ihe.net/ITI/mCSD/StructureDefinition/IHE.mCSD.OrganizationAffiliation.DocShare",
    "version" : "4.0.0-comment",
    "name" : "MCSDOrganizationAffiliationDocShare"
  },
  {
    "id" : "IHE.mCSD.Practitioner",
    "type" : "StructureDefinition",
    "url" : "https://profiles.ihe.net/ITI/mCSD/StructureDefinition/IHE.mCSD.Practitioner",
    "version" : "4.0.0-comment",
    "name" : "MCSDPractitioner"
  },
  {
    "id" : "IHE.mCSD.PractitionerRole",
    "type" : "StructureDefinition",
    "url" : "https://profiles.ihe.net/ITI/mCSD/StructureDefinition/IHE.mCSD.PractitionerRole",
    "version" : "4.0.0-comment",
    "name" : "MCSDPractitionerRole"
  },
  {
    "id" : "IHE.mCSD.PurposeOfUse",
    "type" : "StructureDefinition",
    "url" : "https://profiles.ihe.net/ITI/mCSD/StructureDefinition/IHE.mCSD.PurposeOfUse",
    "version" : "4.0.0-comment",
    "name" : "MCSDPurposeOfUse"
  },
  {
    "id" : "ihe-endpointspecifictype",
    "type" : "StructureDefinition",
    "url" : "https://profiles.ihe.net/ITI/mCSD/StructureDefinition/ihe-endpointspecifictype",
    "version" : "4.0.0-comment",
    "name" : "EndpointSpecificType"
  },
  {
    "id" : "IHE.mCSD.Organization.Location.Types",
    "type" : "ValueSet",
    "url" : "https://profiles.ihe.net/ITI/mCSD/ValueSet/IHE.mCSD.Organization.Location.Types",
    "version" : "4.0.0-comment",
    "name" : "MCSDOrganizationLocationTypeValueSet"
  },
  {
    "id" : "MCSDEndpointIdentifierTypeValueSet",
    "type" : "ValueSet",
    "url" : "https://profiles.ihe.net/ITI/mCSD/ValueSet/MCSDEndpointIdentifierTypeValueSet",
    "version" : "4.0.0-comment",
    "name" : "MCSDEndpointIdentifierTypeValueSet"
  },
  {
    "id" : "MCSDEndpointTypesCoreDocShareVS",
    "type" : "ValueSet",
    "url" : "https://profiles.ihe.net/ITI/mCSD/ValueSet/MCSDEndpointTypesCoreDocShareVS",
    "version" : "4.0.0-comment",
    "name" : "MCSDEndpointTypesCoreDocShareVS"
  },
  {
    "id" : "MCSDEndpointTypesVS",
    "type" : "ValueSet",
    "url" : "https://profiles.ihe.net/ITI/mCSD/ValueSet/MCSDEndpointTypesVS",
    "version" : "4.0.0-comment",
    "name" : "MCSDEndpointTypesVS"
  },
  {
    "id" : "MCSDOrgAffTypesVS",
    "type" : "ValueSet",
    "url" : "https://profiles.ihe.net/ITI/mCSD/ValueSet/MCSDOrgAffTypesVS",
    "version" : "4.0.0-comment",
    "name" : "MCSDOrgAffTypesVS"
  },
  {
    "id" : "MCSDOrganizationIdentifierTypeValueSet",
    "type" : "ValueSet",
    "url" : "https://profiles.ihe.net/ITI/mCSD/ValueSet/MCSDOrganizationIdentifierTypeValueSet",
    "version" : "4.0.0-comment",
    "name" : "MCSDOrganizationIdentifierTypeValueSet"
  }
]
