{
  "date" : "Wed, 12 Mar, 2025 10:59:00 -0500",
  "doco" : "For each file: start is seconds after start activity occurred. Length = milliseconds activity took",
  "files" : [
    {
      "name" : "\\fsh-generated\\resources\\ImplementationGuide-ihe.iti.mcsd.json",
      "size" : 39502,
      "processes" : [
        {
          "activity" : "load",
          "start" : 68,
          "length" : 31
        },
        {
          "activity" : "generateNarratives",
          "start" : 71,
          "length" : 413
        },
        {
          "activity" : "validate",
          "start" : 89,
          "length" : 3601
        },
        {
          "activity" : "scanForUsageStats",
          "start" : 109,
          "length" : 2
        },
        {
          "activity" : "validate",
          "start" : 109,
          "length" : 3
        },
        {
          "activity" : "generate1",
          "start" : 115,
          "length" : 338
        },
        {
          "activity" : "generate2",
          "start" : 136,
          "length" : 422
        },
        {
          "activity" : "generateExampleZip",
          "start" : 301,
          "length" : 2
        },
        {
          "activity" : "generateValidationPack",
          "start" : 303,
          "length" : 26
        },
        {
          "activity" : "scanExamplesForR5",
          "start" : 348,
          "length" : 7
        }
      ]
    },
    {
      "name" : "fsh-generated/resources/AuditEvent-ex-AuditMcsdCareServicesCreate.json",
      "size" : 2201,
      "processes" : [
        {
          "activity" : "loadResources",
          "start" : 67,
          "length" : 15
        },
        {
          "activity" : "generateNarratives",
          "start" : 71,
          "length" : 91
        },
        {
          "activity" : "validate",
          "start" : 109,
          "length" : 1338
        },
        {
          "activity" : "generate1",
          "start" : 116,
          "length" : 49
        },
        {
          "activity" : "generate2",
          "start" : 136,
          "length" : 155
        }
      ]
    },
    {
      "name" : "fsh-generated/resources/AuditEvent-ex-AuditMcsdCareServicesDelete.json",
      "size" : 2212,
      "processes" : [
        {
          "activity" : "generateNarratives",
          "start" : 71,
          "length" : 12
        },
        {
          "activity" : "validate",
          "start" : 110,
          "length" : 40
        },
        {
          "activity" : "generate1",
          "start" : 116,
          "length" : 44
        },
        {
          "activity" : "generate2",
          "start" : 137,
          "length" : 75
        },
        {
          "activity" : "generateExampleZip",
          "start" : 301,
          "length" : 1
        }
      ]
    },
    {
      "name" : "fsh-generated/resources/AuditEvent-ex-AuditMcsdCareServicesProcess.json",
      "size" : 2185,
      "processes" : [
        {
          "activity" : "loadResources",
          "start" : 67,
          "length" : 16
        },
        {
          "activity" : "generateNarratives",
          "start" : 71,
          "length" : 13
        },
        {
          "activity" : "validate",
          "start" : 110,
          "length" : 245
        },
        {
          "activity" : "generate1",
          "start" : 116,
          "length" : 46
        },
        {
          "activity" : "generate2",
          "start" : 137,
          "length" : 56
        },
        {
          "activity" : "generateExampleZip",
          "start" : 301,
          "length" : 3
        }
      ]
    },
    {
      "name" : "fsh-generated/resources/AuditEvent-ex-AuditMcsdCareServicesQuery.json",
      "size" : 2215,
      "processes" : [
        {
          "activity" : "checkR4R4B",
          "start" : 71,
          "length" : 15
        },
        {
          "activity" : "generateNarratives",
          "start" : 71,
          "length" : 24
        },
        {
          "activity" : "validate",
          "start" : 110,
          "length" : 1417
        },
        {
          "activity" : "generate1",
          "start" : 116,
          "length" : 45
        },
        {
          "activity" : "generate2",
          "start" : 137,
          "length" : 67
        },
        {
          "activity" : "generateExampleZip",
          "start" : 302,
          "length" : 1
        }
      ]
    },
    {
      "name" : "fsh-generated/resources/AuditEvent-ex-AuditMcsdCareServicesRead.json",
      "size" : 2047,
      "processes" : [
        {
          "activity" : "loadResources",
          "start" : 67,
          "length" : 15
        },
        {
          "activity" : "generateNarratives",
          "start" : 71,
          "length" : 15
        },
        {
          "activity" : "validate",
          "start" : 112,
          "length" : 237
        },
        {
          "activity" : "generate1",
          "start" : 116,
          "length" : 42
        },
        {
          "activity" : "generate2",
          "start" : 137,
          "length" : 54
        }
      ]
    },
    {
      "name" : "fsh-generated/resources/AuditEvent-ex-AuditMcsdCareServicesUpdate.json",
      "size" : 2201,
      "processes" : [
        {
          "activity" : "generateNarratives",
          "start" : 71,
          "length" : 13
        },
        {
          "activity" : "validate",
          "start" : 112,
          "length" : 35
        },
        {
          "activity" : "generate1",
          "start" : 116,
          "length" : 43
        },
        {
          "activity" : "generate2",
          "start" : 137,
          "length" : 48
        },
        {
          "activity" : "generateExampleZip",
          "start" : 302,
          "length" : 1
        }
      ]
    },
    {
      "name" : "fsh-generated/resources/AuditEvent-ex-AuditMcsdCareServicesUpdates.json",
      "size" : 2256,
      "processes" : [
        {
          "activity" : "loadResources",
          "start" : 67,
          "length" : 16
        },
        {
          "activity" : "generateNarratives",
          "start" : 71,
          "length" : 23
        },
        {
          "activity" : "validate",
          "start" : 112,
          "length" : 1242
        },
        {
          "activity" : "generate1",
          "start" : 116,
          "length" : 47
        },
        {
          "activity" : "generate2",
          "start" : 137,
          "length" : 47
        }
      ]
    },
    {
      "name" : "fsh-generated/resources/Bundle-Example-MCSD.json",
      "size" : 20365,
      "processes" : [
        {
          "activity" : "loadResources",
          "start" : 67,
          "length" : 16
        },
        {
          "activity" : "load",
          "start" : 67,
          "length" : 62
        },
        {
          "activity" : "generateNarratives",
          "start" : 71,
          "length" : 3086
        },
        {
          "activity" : "scanForUsageStats",
          "start" : 109,
          "length" : 1
        },
        {
          "activity" : "validate",
          "start" : 113,
          "length" : 1496
        },
        {
          "activity" : "generate1",
          "start" : 116,
          "length" : 162
        },
        {
          "activity" : "generate2",
          "start" : 137,
          "length" : 233
        },
        {
          "activity" : "generateExampleZip",
          "start" : 301,
          "length" : 1
        },
        {
          "activity" : "scanExamplesForR5",
          "start" : 348,
          "length" : 1
        }
      ]
    },
    {
      "name" : "fsh-generated/resources/CapabilityStatement-IHE.mCSD.DataSource.json",
      "size" : 11093,
      "processes" : [
        {
          "activity" : "load",
          "start" : 68,
          "length" : 16
        },
        {
          "activity" : "generateNarratives",
          "start" : 75,
          "length" : 32
        },
        {
          "activity" : "validate",
          "start" : 87,
          "length" : 798
        },
        {
          "activity" : "validate",
          "start" : 115,
          "length" : 3
        },
        {
          "activity" : "generate1",
          "start" : 116,
          "length" : 117
        },
        {
          "activity" : "generate2",
          "start" : 137,
          "length" : 77
        },
        {
          "activity" : "makeDependencies",
          "start" : 195,
          "length" : 1
        },
        {
          "activity" : "generateValidationPack",
          "start" : 303,
          "length" : 6
        },
        {
          "activity" : "scanExamplesForR5",
          "start" : 348,
          "length" : 1
        }
      ]
    },
    {
      "name" : "fsh-generated/resources/CapabilityStatement-IHE.mCSD.Directory.Feed.json",
      "size" : 11133,
      "processes" : [
        {
          "activity" : "loadResources",
          "start" : 67,
          "length" : 15
        },
        {
          "activity" : "load",
          "start" : 68,
          "length" : 15
        },
        {
          "activity" : "generateNarratives",
          "start" : 75,
          "length" : 27
        },
        {
          "activity" : "validate",
          "start" : 88,
          "length" : 71
        },
        {
          "activity" : "validate",
          "start" : 115,
          "length" : 3
        },
        {
          "activity" : "generate1",
          "start" : 116,
          "length" : 112
        },
        {
          "activity" : "generate2",
          "start" : 137,
          "length" : 76
        },
        {
          "activity" : "generateValidationPack",
          "start" : 303,
          "length" : 2
        }
      ]
    },
    {
      "name" : "fsh-generated/resources/CapabilityStatement-IHE.mCSD.Directory.LocationDistance.json",
      "size" : 2382,
      "processes" : [
        {
          "activity" : "loadResources",
          "start" : 67,
          "length" : 16
        },
        {
          "activity" : "load",
          "start" : 68,
          "length" : 32
        },
        {
          "activity" : "generateNarratives",
          "start" : 75,
          "length" : 16
        },
        {
          "activity" : "validate",
          "start" : 88,
          "length" : 19
        },
        {
          "activity" : "validate",
          "start" : 115,
          "length" : 3
        },
        {
          "activity" : "generate1",
          "start" : 117,
          "length" : 59
        },
        {
          "activity" : "generate2",
          "start" : 137,
          "length" : 51
        },
        {
          "activity" : "generateValidationPack",
          "start" : 303,
          "length" : 2
        },
        {
          "activity" : "scanExamplesForR5",
          "start" : 348,
          "length" : 1
        }
      ]
    },
    {
      "name" : "fsh-generated/resources/CapabilityStatement-IHE.mCSD.Directory.Update.json",
      "size" : 9180,
      "processes" : [
        {
          "activity" : "load",
          "start" : 68,
          "length" : 15
        },
        {
          "activity" : "generateNarratives",
          "start" : 75,
          "length" : 26
        },
        {
          "activity" : "validate",
          "start" : 88,
          "length" : 61
        },
        {
          "activity" : "validate",
          "start" : 115,
          "length" : 4
        },
        {
          "activity" : "generate1",
          "start" : 117,
          "length" : 123
        },
        {
          "activity" : "generate2",
          "start" : 137,
          "length" : 52
        },
        {
          "activity" : "generateValidationPack",
          "start" : 303,
          "length" : 2
        }
      ]
    },
    {
      "name" : "fsh-generated/resources/CapabilityStatement-IHE.mCSD.Directory.json",
      "size" : 26678,
      "processes" : [
        {
          "activity" : "loadResources",
          "start" : 67,
          "length" : 16
        },
        {
          "activity" : "load",
          "start" : 68,
          "length" : 16
        },
        {
          "activity" : "generateNarratives",
          "start" : 75,
          "length" : 40
        },
        {
          "activity" : "validate",
          "start" : 88,
          "length" : 225
        },
        {
          "activity" : "validate",
          "start" : 115,
          "length" : 3
        },
        {
          "activity" : "generate1",
          "start" : 117,
          "length" : 179
        },
        {
          "activity" : "generate2",
          "start" : 137,
          "length" : 67
        },
        {
          "activity" : "generateValidationPack",
          "start" : 303,
          "length" : 8
        },
        {
          "activity" : "scanExamplesForR5",
          "start" : 348,
          "length" : 2
        }
      ]
    },
    {
      "name" : "fsh-generated/resources/CapabilityStatement-IHE.mCSD.QueryClient.LocationDistance.json",
      "size" : 2397,
      "processes" : [
        {
          "activity" : "generateNarratives",
          "start" : 75,
          "length" : 14
        },
        {
          "activity" : "validate",
          "start" : 89,
          "length" : 22
        },
        {
          "activity" : "validate",
          "start" : 115,
          "length" : 3
        },
        {
          "activity" : "generate1",
          "start" : 117,
          "length" : 63
        },
        {
          "activity" : "generate2",
          "start" : 137,
          "length" : 73
        },
        {
          "activity" : "generateValidationPack",
          "start" : 303,
          "length" : 1
        }
      ]
    },
    {
      "name" : "fsh-generated/resources/CapabilityStatement-IHE.mCSD.QueryClient.json",
      "size" : 27192,
      "processes" : [
        {
          "activity" : "loadResources",
          "start" : 67,
          "length" : 15
        },
        {
          "activity" : "load",
          "start" : 68,
          "length" : 31
        },
        {
          "activity" : "generateNarratives",
          "start" : 75,
          "length" : 35
        },
        {
          "activity" : "validate",
          "start" : 89,
          "length" : 184
        },
        {
          "activity" : "validate",
          "start" : 89,
          "length" : 1
        },
        {
          "activity" : "scanForUsageStats",
          "start" : 109,
          "length" : 1
        },
        {
          "activity" : "validate",
          "start" : 115,
          "length" : 3
        },
        {
          "activity" : "generate1",
          "start" : 117,
          "length" : 167
        },
        {
          "activity" : "generate2",
          "start" : 137,
          "length" : 63
        },
        {
          "activity" : "makeDependencies",
          "start" : 195,
          "length" : 1
        },
        {
          "activity" : "generateExampleZip",
          "start" : 301,
          "length" : 1
        },
        {
          "activity" : "generateValidationPack",
          "start" : 303,
          "length" : 5
        },
        {
          "activity" : "scanExamplesForR5",
          "start" : 348,
          "length" : 2
        }
      ]
    },
    {
      "name" : "fsh-generated/resources/CapabilityStatement-IHE.mCSD.UpdateClient.json",
      "size" : 9135,
      "processes" : [
        {
          "activity" : "loadResources",
          "start" : 67,
          "length" : 16
        },
        {
          "activity" : "load",
          "start" : 68,
          "length" : 16
        },
        {
          "activity" : "generateNarratives",
          "start" : 75,
          "length" : 23
        },
        {
          "activity" : "validate",
          "start" : 89,
          "length" : 77
        },
        {
          "activity" : "validate",
          "start" : 115,
          "length" : 5
        },
        {
          "activity" : "generate1",
          "start" : 117,
          "length" : 115
        },
        {
          "activity" : "generate2",
          "start" : 138,
          "length" : 52
        },
        {
          "activity" : "generateValidationPack",
          "start" : 303,
          "length" : 6
        },
        {
          "activity" : "scanExamplesForR5",
          "start" : 348,
          "length" : 1
        }
      ]
    },
    {
      "name" : "fsh-generated/resources/CodeSystem-IHE.mCSD.Organization.Location.Types.json",
      "size" : 643,
      "processes" : [
        {
          "activity" : "load",
          "start" : 67,
          "length" : 16
        },
        {
          "activity" : "generateNarratives",
          "start" : 75,
          "length" : 15
        },
        {
          "activity" : "validate",
          "start" : 76,
          "length" : 553
        },
        {
          "activity" : "checkConformanceResources",
          "start" : 93,
          "length" : 2
        },
        {
          "activity" : "validate",
          "start" : 115,
          "length" : 6
        },
        {
          "activity" : "generate1",
          "start" : 117,
          "length" : 33
        },
        {
          "activity" : "generate2",
          "start" : 138,
          "length" : 6566
        },
        {
          "activity" : "generateValidationPack",
          "start" : 303,
          "length" : 1
        }
      ]
    },
    {
      "name" : "fsh-generated/resources/CodeSystem-MCSDEndpointIdentifierTypes.json",
      "size" : 739,
      "processes" : [
        {
          "activity" : "load",
          "start" : 67,
          "length" : 15
        },
        {
          "activity" : "generateNarratives",
          "start" : 75,
          "length" : 14
        },
        {
          "activity" : "validate",
          "start" : 77,
          "length" : 15
        },
        {
          "activity" : "checkConformanceResources",
          "start" : 93,
          "length" : 1
        },
        {
          "activity" : "validate",
          "start" : 115,
          "length" : 3
        },
        {
          "activity" : "generate1",
          "start" : 117,
          "length" : 35
        },
        {
          "activity" : "generate2",
          "start" : 144,
          "length" : 229
        },
        {
          "activity" : "generateExampleZip",
          "start" : 302,
          "length" : 1
        },
        {
          "activity" : "generateValidationPack",
          "start" : 303,
          "length" : 1
        }
      ]
    },
    {
      "name" : "fsh-generated/resources/CodeSystem-MCSDEndpointTypes.json",
      "size" : 8499,
      "processes" : [
        {
          "activity" : "loadResources",
          "start" : 67,
          "length" : 15
        },
        {
          "activity" : "load",
          "start" : 67,
          "length" : 16
        },
        {
          "activity" : "generateNarratives",
          "start" : 75,
          "length" : 16
        },
        {
          "activity" : "validate",
          "start" : 77,
          "length" : 47
        },
        {
          "activity" : "checkConformanceResources",
          "start" : 93,
          "length" : 2
        },
        {
          "activity" : "validate",
          "start" : 115,
          "length" : 4
        },
        {
          "activity" : "generate1",
          "start" : 117,
          "length" : 96
        },
        {
          "activity" : "generate2",
          "start" : 144,
          "length" : 230
        },
        {
          "activity" : "generateValidationPack",
          "start" : 303,
          "length" : 2
        },
        {
          "activity" : "scanExamplesForR5",
          "start" : 348,
          "length" : 1
        }
      ]
    },
    {
      "name" : "fsh-generated/resources/CodeSystem-MCSDOrgAffTypes.json",
      "size" : 541,
      "processes" : [
        {
          "activity" : "generateNarratives",
          "start" : 75,
          "length" : 13
        },
        {
          "activity" : "validate",
          "start" : 77,
          "length" : 16
        },
        {
          "activity" : "checkConformanceResources",
          "start" : 93,
          "length" : 1
        },
        {
          "activity" : "validate",
          "start" : 115,
          "length" : 6
        },
        {
          "activity" : "generate1",
          "start" : 117,
          "length" : 33
        },
        {
          "activity" : "generate2",
          "start" : 145,
          "length" : 176
        },
        {
          "activity" : "generateValidationPack",
          "start" : 303,
          "length" : 1
        }
      ]
    },
    {
      "name" : "fsh-generated/resources/CodeSystem-MCSDOrganizationIdentifierTypes.json",
      "size" : 734,
      "processes" : [
        {
          "activity" : "loadResources",
          "start" : 67,
          "length" : 16
        },
        {
          "activity" : "load",
          "start" : 67,
          "length" : 16
        },
        {
          "activity" : "generateNarratives",
          "start" : 75,
          "length" : 13
        },
        {
          "activity" : "validate",
          "start" : 77,
          "length" : 15
        },
        {
          "activity" : "checkConformanceResources",
          "start" : 93,
          "length" : 1
        },
        {
          "activity" : "validate",
          "start" : 115,
          "length" : 3
        },
        {
          "activity" : "generate1",
          "start" : 117,
          "length" : 35
        },
        {
          "activity" : "generate2",
          "start" : 145,
          "length" : 173
        }
      ]
    },
    {
      "name" : "fsh-generated/resources/CodeSystem-mcsd-example-hierarchy.json",
      "size" : 559,
      "processes" : [
        {
          "activity" : "load",
          "start" : 67,
          "length" : 15
        },
        {
          "activity" : "generateNarratives",
          "start" : 75,
          "length" : 10
        },
        {
          "activity" : "validate",
          "start" : 77,
          "length" : 16
        },
        {
          "activity" : "checkConformanceResources",
          "start" : 93,
          "length" : 2
        },
        {
          "activity" : "validate",
          "start" : 115,
          "length" : 3
        },
        {
          "activity" : "generate1",
          "start" : 117,
          "length" : 34
        },
        {
          "activity" : "generate2",
          "start" : 145,
          "length" : 130
        },
        {
          "activity" : "generateExampleZip",
          "start" : 302,
          "length" : 1
        }
      ]
    },
    {
      "name" : "fsh-generated/resources/Device-ex-device.json",
      "size" : 52,
      "processes" : [
        {
          "activity" : "generateNarratives",
          "start" : 75,
          "length" : 3
        },
        {
          "activity" : "validate",
          "start" : 115,
          "length" : 11
        },
        {
          "activity" : "generate1",
          "start" : 117,
          "length" : 24
        },
        {
          "activity" : "generate2",
          "start" : 145,
          "length" : 47
        }
      ]
    },
    {
      "name" : "fsh-generated/resources/Endpoint-ex-endpointDicom.json",
      "size" : 1124,
      "processes" : [
        {
          "activity" : "loadResources",
          "start" : 67,
          "length" : 16
        },
        {
          "activity" : "generateNarratives",
          "start" : 75,
          "length" : 11
        },
        {
          "activity" : "validate",
          "start" : 115,
          "length" : 23
        },
        {
          "activity" : "generate1",
          "start" : 118,
          "length" : 32
        },
        {
          "activity" : "generate2",
          "start" : 145,
          "length" : 40
        }
      ]
    },
    {
      "name" : "fsh-generated/resources/Endpoint-ex-endpointXCAquery.json",
      "size" : 1777,
      "processes" : [
        {
          "activity" : "generateNarratives",
          "start" : 75,
          "length" : 13
        },
        {
          "activity" : "validate",
          "start" : 115,
          "length" : 18
        },
        {
          "activity" : "generate1",
          "start" : 118,
          "length" : 35
        },
        {
          "activity" : "generate2",
          "start" : 145,
          "length" : 42
        },
        {
          "activity" : "generateExampleZip",
          "start" : 301,
          "length" : 1
        }
      ]
    },
    {
      "name" : "fsh-generated/resources/Endpoint-ex-endpointXCAretrieve.json",
      "size" : 1786,
      "processes" : [
        {
          "activity" : "generateNarratives",
          "start" : 75,
          "length" : 13
        },
        {
          "activity" : "validate",
          "start" : 115,
          "length" : 24
        },
        {
          "activity" : "generate1",
          "start" : 118,
          "length" : 35
        },
        {
          "activity" : "generate2",
          "start" : 145,
          "length" : 40
        }
      ]
    },
    {
      "name" : "fsh-generated/resources/HealthcareService-MCSDHealthcareService-Example.json",
      "size" : 535,
      "processes" : [
        {
          "activity" : "loadResources",
          "start" : 67,
          "length" : 15
        },
        {
          "activity" : "generateNarratives",
          "start" : 75,
          "length" : 3
        },
        {
          "activity" : "validate",
          "start" : 115,
          "length" : 12
        },
        {
          "activity" : "generate1",
          "start" : 118,
          "length" : 29
        },
        {
          "activity" : "generate2",
          "start" : 145,
          "length" : 41
        },
        {
          "activity" : "generateExampleZip",
          "start" : 301,
          "length" : 1
        }
      ]
    },
    {
      "name" : "fsh-generated/resources/Location-MCSDFacilityLocation-Example.json",
      "size" : 975,
      "processes" : [
        {
          "activity" : "generateNarratives",
          "start" : 75,
          "length" : 6
        },
        {
          "activity" : "validate",
          "start" : 115,
          "length" : 17
        },
        {
          "activity" : "generate1",
          "start" : 118,
          "length" : 32
        },
        {
          "activity" : "generate2",
          "start" : 145,
          "length" : 42
        },
        {
          "activity" : "generateExampleZip",
          "start" : 301,
          "length" : 1
        }
      ]
    },
    {
      "name" : "fsh-generated/resources/Location-MCSDJurisdictionLocation-Example.json",
      "size" : 759,
      "processes" : [
        {
          "activity" : "generateNarratives",
          "start" : 75,
          "length" : 4
        },
        {
          "activity" : "validate",
          "start" : 115,
          "length" : 17
        },
        {
          "activity" : "generate1",
          "start" : 118,
          "length" : 30
        },
        {
          "activity" : "generate2",
          "start" : 145,
          "length" : 60
        }
      ]
    },
    {
      "name" : "fsh-generated/resources/Location-MCSDLocation-Example.json",
      "size" : 656,
      "processes" : [
        {
          "activity" : "loadResources",
          "start" : 67,
          "length" : 16
        },
        {
          "activity" : "generateNarratives",
          "start" : 75,
          "length" : 4
        },
        {
          "activity" : "validate",
          "start" : 115,
          "length" : 15
        },
        {
          "activity" : "generate1",
          "start" : 118,
          "length" : 30
        },
        {
          "activity" : "generate2",
          "start" : 145,
          "length" : 39
        }
      ]
    },
    {
      "name" : "fsh-generated/resources/Location-MCSDLocationDistance-Example.json",
      "size" : 696,
      "processes" : [
        {
          "activity" : "load-configure",
          "start" : 71,
          "length" : 16
        },
        {
          "activity" : "generateNarratives",
          "start" : 75,
          "length" : 6
        },
        {
          "activity" : "validate",
          "start" : 115,
          "length" : 11
        },
        {
          "activity" : "generate1",
          "start" : 118,
          "length" : 31
        },
        {
          "activity" : "generate2",
          "start" : 145,
          "length" : 36
        },
        {
          "activity" : "generateExampleZip",
          "start" : 302,
          "length" : 1
        }
      ]
    },
    {
      "name" : "fsh-generated/resources/Organization-MCSDFacilityOrganization-Example.json",
      "size" : 574,
      "processes" : [
        {
          "activity" : "loadResources",
          "start" : 67,
          "length" : 16
        },
        {
          "activity" : "generateNarratives",
          "start" : 75,
          "length" : 6
        },
        {
          "activity" : "validate",
          "start" : 115,
          "length" : 13
        },
        {
          "activity" : "generate1",
          "start" : 118,
          "length" : 29
        },
        {
          "activity" : "generate2",
          "start" : 145,
          "length" : 37
        },
        {
          "activity" : "generateExampleZip",
          "start" : 301,
          "length" : 1
        }
      ]
    },
    {
      "name" : "fsh-generated/resources/Organization-MCSDJurisdictionOrganization-Example.json",
      "size" : 502,
      "processes" : [
        {
          "activity" : "generateNarratives",
          "start" : 75,
          "length" : 4
        },
        {
          "activity" : "validate",
          "start" : 115,
          "length" : 10
        },
        {
          "activity" : "generate1",
          "start" : 118,
          "length" : 29
        },
        {
          "activity" : "generate2",
          "start" : 146,
          "length" : 34
        }
      ]
    },
    {
      "name" : "fsh-generated/resources/Organization-MCSDOrganization-ExamplePartner.json",
      "size" : 442,
      "processes" : [
        {
          "activity" : "generateNarratives",
          "start" : 75,
          "length" : 4
        },
        {
          "activity" : "validate",
          "start" : 115,
          "length" : 10
        },
        {
          "activity" : "generate1",
          "start" : 118,
          "length" : 27
        },
        {
          "activity" : "generate2",
          "start" : 146,
          "length" : 34
        }
      ]
    },
    {
      "name" : "fsh-generated/resources/Organization-ex-OrgA.json",
      "size" : 532,
      "processes" : [
        {
          "activity" : "loadResources",
          "start" : 67,
          "length" : 15
        },
        {
          "activity" : "generateNarratives",
          "start" : 75,
          "length" : 4
        },
        {
          "activity" : "validate",
          "start" : 115,
          "length" : 9
        },
        {
          "activity" : "generate1",
          "start" : 118,
          "length" : 28
        },
        {
          "activity" : "generate2",
          "start" : 146,
          "length" : 33
        }
      ]
    },
    {
      "name" : "fsh-generated/resources/Organization-ex-OrgB.json",
      "size" : 793,
      "processes" : [
        {
          "activity" : "generateNarratives",
          "start" : 75,
          "length" : 4
        },
        {
          "activity" : "validate",
          "start" : 115,
          "length" : 14
        },
        {
          "activity" : "generate1",
          "start" : 118,
          "length" : 31
        },
        {
          "activity" : "generate2",
          "start" : 146,
          "length" : 41
        }
      ]
    },
    {
      "name" : "fsh-generated/resources/Organization-ex-OrgC.json",
      "size" : 615,
      "processes" : [
        {
          "activity" : "generateNarratives",
          "start" : 75,
          "length" : 6
        },
        {
          "activity" : "validate",
          "start" : 115,
          "length" : 10
        },
        {
          "activity" : "generate1",
          "start" : 118,
          "length" : 30
        },
        {
          "activity" : "generate2",
          "start" : 146,
          "length" : 41
        }
      ]
    },
    {
      "name" : "fsh-generated/resources/OrganizationAffiliation-MCSDFacilityOrganizationAffiliation-Example.json",
      "size" : 640,
      "processes" : [
        {
          "activity" : "loadResources",
          "start" : 67,
          "length" : 16
        },
        {
          "activity" : "generateNarratives",
          "start" : 75,
          "length" : 5
        },
        {
          "activity" : "validate",
          "start" : 115,
          "length" : 11
        },
        {
          "activity" : "generate1",
          "start" : 118,
          "length" : 30
        },
        {
          "activity" : "generate2",
          "start" : 146,
          "length" : 57
        },
        {
          "activity" : "generateExampleZip",
          "start" : 301,
          "length" : 1
        }
      ]
    },
    {
      "name" : "fsh-generated/resources/OrganizationAffiliation-ex-OrgAff.json",
      "size" : 735,
      "processes" : [
        {
          "activity" : "generateNarratives",
          "start" : 75,
          "length" : 6
        },
        {
          "activity" : "validate",
          "start" : 115,
          "length" : 13
        },
        {
          "activity" : "generate1",
          "start" : 118,
          "length" : 31
        },
        {
          "activity" : "generate2",
          "start" : 146,
          "length" : 56
        },
        {
          "activity" : "generateExampleZip",
          "start" : 302,
          "length" : 1
        }
      ]
    },
    {
      "name" : "fsh-generated/resources/OrganizationAffiliation-ex-OrgAffC.json",
      "size" : 1053,
      "processes" : [
        {
          "activity" : "generateNarratives",
          "start" : 75,
          "length" : 7
        },
        {
          "activity" : "validate",
          "start" : 115,
          "length" : 21
        },
        {
          "activity" : "generate1",
          "start" : 118,
          "length" : 33
        },
        {
          "activity" : "generate2",
          "start" : 146,
          "length" : 54
        }
      ]
    },
    {
      "name" : "fsh-generated/resources/Practitioner-MCSDPractitioner-Example.json",
      "size" : 252,
      "processes" : [
        {
          "activity" : "loadResources",
          "start" : 67,
          "length" : 15
        },
        {
          "activity" : "generateNarratives",
          "start" : 75,
          "length" : 3
        },
        {
          "activity" : "validate",
          "start" : 115,
          "length" : 6
        },
        {
          "activity" : "generate1",
          "start" : 118,
          "length" : 26
        },
        {
          "activity" : "generate2",
          "start" : 146,
          "length" : 73
        }
      ]
    },
    {
      "name" : "fsh-generated/resources/PractitionerRole-MCSDPractitionerRole-Example.json",
      "size" : 764,
      "processes" : [
        {
          "activity" : "generateNarratives",
          "start" : 75,
          "length" : 6
        },
        {
          "activity" : "validate",
          "start" : 115,
          "length" : 15
        },
        {
          "activity" : "generate1",
          "start" : 118,
          "length" : 31
        },
        {
          "activity" : "generate2",
          "start" : 146,
          "length" : 45
        },
        {
          "activity" : "scanExamplesForR5",
          "start" : 348,
          "length" : 1
        }
      ]
    },
    {
      "name" : "fsh-generated/resources/SearchParameter-Endpoint-EndpointSpecificType.json",
      "size" : 592,
      "processes" : [
        {
          "activity" : "load",
          "start" : 68,
          "length" : 16
        },
        {
          "activity" : "generateNarratives",
          "start" : 75,
          "length" : 11
        },
        {
          "activity" : "validate",
          "start" : 87,
          "length" : 15
        },
        {
          "activity" : "validate",
          "start" : 93,
          "length" : 1
        },
        {
          "activity" : "validate",
          "start" : 115,
          "length" : 3
        },
        {
          "activity" : "generate1",
          "start" : 118,
          "length" : 35
        },
        {
          "activity" : "generate2",
          "start" : 146,
          "length" : 43
        },
        {
          "activity" : "generateValidationPack",
          "start" : 303,
          "length" : 1
        }
      ]
    },
    {
      "name" : "fsh-generated/resources/SearchParameter-IHE.mCSD.Search.PurposeOfUse.json",
      "size" : 645,
      "processes" : [
        {
          "activity" : "loadResources",
          "start" : 67,
          "length" : 16
        },
        {
          "activity" : "load",
          "start" : 68,
          "length" : 15
        },
        {
          "activity" : "load",
          "start" : 68,
          "length" : 16
        },
        {
          "activity" : "generateNarratives",
          "start" : 75,
          "length" : 9
        },
        {
          "activity" : "validate",
          "start" : 93,
          "length" : 2
        },
        {
          "activity" : "validate",
          "start" : 115,
          "length" : 4
        },
        {
          "activity" : "generate1",
          "start" : 118,
          "length" : 35
        },
        {
          "activity" : "generate2",
          "start" : 146,
          "length" : 49
        },
        {
          "activity" : "generateExampleZip",
          "start" : 302,
          "length" : 1
        }
      ]
    },
    {
      "name" : "fsh-generated/resources/StructureDefinition-IHE.mCSD.Audit.CareServices.Create.json",
      "size" : 2574,
      "processes" : [
        {
          "activity" : "load",
          "start" : 67,
          "length" : 16
        },
        {
          "activity" : "generateSnapshots",
          "start" : 68,
          "length" : 672
        },
        {
          "activity" : "generateNarratives",
          "start" : 75,
          "length" : 95
        },
        {
          "activity" : "validate",
          "start" : 77,
          "length" : 1922
        },
        {
          "activity" : "checkConformanceResources",
          "start" : 93,
          "length" : 4
        },
        {
          "activity" : "scanForUsageStats",
          "start" : 109,
          "length" : 3
        },
        {
          "activity" : "validate",
          "start" : 115,
          "length" : 7
        },
        {
          "activity" : "generate1",
          "start" : 118,
          "length" : 1117
        },
        {
          "activity" : "generate2",
          "start" : 146,
          "length" : 2564
        },
        {
          "activity" : "generate2",
          "start" : 169,
          "length" : 2105
        },
        {
          "activity" : "generateValidationPack",
          "start" : 303,
          "length" : 40
        },
        {
          "activity" : "scanProfilesForR5",
          "start" : 348,
          "length" : 1
        },
        {
          "activity" : "scanExamplesForR5",
          "start" : 348,
          "length" : 6
        }
      ]
    },
    {
      "name" : "fsh-generated/resources/StructureDefinition-IHE.mCSD.Audit.CareServices.Delete.json",
      "size" : 2574,
      "processes" : [
        {
          "activity" : "loadResources",
          "start" : 67,
          "length" : 16
        },
        {
          "activity" : "load",
          "start" : 67,
          "length" : 15
        },
        {
          "activity" : "generateSnapshots",
          "start" : 69,
          "length" : 250
        },
        {
          "activity" : "generateNarratives",
          "start" : 75,
          "length" : 75
        },
        {
          "activity" : "validate",
          "start" : 79,
          "length" : 1703
        },
        {
          "activity" : "checkConformanceResources",
          "start" : 93,
          "length" : 1
        },
        {
          "activity" : "scanForUsageStats",
          "start" : 109,
          "length" : 3
        },
        {
          "activity" : "validate",
          "start" : 115,
          "length" : 3
        },
        {
          "activity" : "generate1",
          "start" : 119,
          "length" : 1214
        },
        {
          "activity" : "generate2",
          "start" : 149,
          "length" : 1809
        },
        {
          "activity" : "generate2",
          "start" : 171,
          "length" : 1104
        },
        {
          "activity" : "generateValidationPack",
          "start" : 303,
          "length" : 31
        },
        {
          "activity" : "scanExamplesForR5",
          "start" : 348,
          "length" : 5
        }
      ]
    },
    {
      "name" : "fsh-generated/resources/StructureDefinition-IHE.mCSD.Audit.CareServices.Process.json",
      "size" : 2013,
      "processes" : [
        {
          "activity" : "load",
          "start" : 67,
          "length" : 16
        },
        {
          "activity" : "generateSnapshots",
          "start" : 69,
          "length" : 218
        },
        {
          "activity" : "generateNarratives",
          "start" : 75,
          "length" : 67
        },
        {
          "activity" : "validate",
          "start" : 81,
          "length" : 1125
        },
        {
          "activity" : "checkConformanceResources",
          "start" : 93,
          "length" : 4
        },
        {
          "activity" : "scanForUsageStats",
          "start" : 109,
          "length" : 3
        },
        {
          "activity" : "validate",
          "start" : 115,
          "length" : 3
        },
        {
          "activity" : "generate1",
          "start" : 120,
          "length" : 1109
        },
        {
          "activity" : "generate2",
          "start" : 150,
          "length" : 2090
        },
        {
          "activity" : "generate2",
          "start" : 172,
          "length" : 781
        },
        {
          "activity" : "generateValidationPack",
          "start" : 303,
          "length" : 23
        },
        {
          "activity" : "scanExamplesForR5",
          "start" : 348,
          "length" : 5
        }
      ]
    },
    {
      "name" : "fsh-generated/resources/StructureDefinition-IHE.mCSD.Audit.CareServices.Query.json",
      "size" : 1283,
      "processes" : [
        {
          "activity" : "load",
          "start" : 67,
          "length" : 16
        },
        {
          "activity" : "generateSnapshots",
          "start" : 69,
          "length" : 188
        },
        {
          "activity" : "generateNarratives",
          "start" : 75,
          "length" : 121
        },
        {
          "activity" : "validate",
          "start" : 82,
          "length" : 953
        },
        {
          "activity" : "checkConformanceResources",
          "start" : 93,
          "length" : 2
        },
        {
          "activity" : "scanForUsageStats",
          "start" : 109,
          "length" : 2
        },
        {
          "activity" : "validate",
          "start" : 115,
          "length" : 6
        },
        {
          "activity" : "generate1",
          "start" : 122,
          "length" : 1049
        },
        {
          "activity" : "generate2",
          "start" : 153,
          "length" : 1672
        },
        {
          "activity" : "generate2",
          "start" : 173,
          "length" : 620
        },
        {
          "activity" : "generateValidationPack",
          "start" : 303,
          "length" : 22
        },
        {
          "activity" : "scanProfilesForR5",
          "start" : 348,
          "length" : 1
        },
        {
          "activity" : "scanExamplesForR5",
          "start" : 348,
          "length" : 4
        }
      ]
    },
    {
      "name" : "fsh-generated/resources/StructureDefinition-IHE.mCSD.Audit.CareServices.Read.json",
      "size" : 2571,
      "processes" : [
        {
          "activity" : "loadResources",
          "start" : 67,
          "length" : 15
        },
        {
          "activity" : "load",
          "start" : 67,
          "length" : 15
        },
        {
          "activity" : "generateSnapshots",
          "start" : 69,
          "length" : 187
        },
        {
          "activity" : "generateNarratives",
          "start" : 75,
          "length" : 64
        },
        {
          "activity" : "validate",
          "start" : 83,
          "length" : 844
        },
        {
          "activity" : "checkConformanceResources",
          "start" : 93,
          "length" : 2
        },
        {
          "activity" : "scanForUsageStats",
          "start" : 109,
          "length" : 3
        },
        {
          "activity" : "validate",
          "start" : 115,
          "length" : 7
        },
        {
          "activity" : "generate1",
          "start" : 123,
          "length" : 1089
        },
        {
          "activity" : "generate2",
          "start" : 154,
          "length" : 1982
        },
        {
          "activity" : "generate2",
          "start" : 173,
          "length" : 608
        },
        {
          "activity" : "generateExampleZip",
          "start" : 301,
          "length" : 1
        },
        {
          "activity" : "generateValidationPack",
          "start" : 303,
          "length" : 23
        },
        {
          "activity" : "scanExamplesForR5",
          "start" : 348,
          "length" : 5
        }
      ]
    },
    {
      "name" : "fsh-generated/resources/StructureDefinition-IHE.mCSD.Audit.CareServices.Update.json",
      "size" : 2574,
      "processes" : [
        {
          "activity" : "load",
          "start" : 67,
          "length" : 16
        },
        {
          "activity" : "generateSnapshots",
          "start" : 69,
          "length" : 203
        },
        {
          "activity" : "generateNarratives",
          "start" : 75,
          "length" : 58
        },
        {
          "activity" : "validate",
          "start" : 83,
          "length" : 828
        },
        {
          "activity" : "checkConformanceResources",
          "start" : 93,
          "length" : 1
        },
        {
          "activity" : "scanForUsageStats",
          "start" : 109,
          "length" : 3
        },
        {
          "activity" : "validate",
          "start" : 115,
          "length" : 3
        },
        {
          "activity" : "generate1",
          "start" : 124,
          "length" : 1098
        },
        {
          "activity" : "generate2",
          "start" : 156,
          "length" : 1696
        },
        {
          "activity" : "generate2",
          "start" : 174,
          "length" : 616
        },
        {
          "activity" : "generateValidationPack",
          "start" : 303,
          "length" : 27
        },
        {
          "activity" : "scanExamplesForR5",
          "start" : 348,
          "length" : 10
        }
      ]
    },
    {
      "name" : "fsh-generated/resources/StructureDefinition-IHE.mCSD.Audit.CareServices.Updates.json",
      "size" : 8411,
      "processes" : [
        {
          "activity" : "loadResources",
          "start" : 67,
          "length" : 16
        },
        {
          "activity" : "load",
          "start" : 67,
          "length" : 15
        },
        {
          "activity" : "generateSnapshots",
          "start" : 70,
          "length" : 282
        },
        {
          "activity" : "generateNarratives",
          "start" : 75,
          "length" : 176
        },
        {
          "activity" : "validate",
          "start" : 84,
          "length" : 844
        },
        {
          "activity" : "checkConformanceResources",
          "start" : 93,
          "length" : 2
        },
        {
          "activity" : "scanForUsageStats",
          "start" : 109,
          "length" : 3
        },
        {
          "activity" : "validate",
          "start" : 115,
          "length" : 6
        },
        {
          "activity" : "generate1",
          "start" : 125,
          "length" : 1523
        },
        {
          "activity" : "generate2",
          "start" : 158,
          "length" : 2392
        },
        {
          "activity" : "generate2",
          "start" : 175,
          "length" : 814
        },
        {
          "activity" : "generateValidationPack",
          "start" : 303,
          "length" : 30
        },
        {
          "activity" : "scanProfilesForR5",
          "start" : 348,
          "length" : 1
        },
        {
          "activity" : "scanExamplesForR5",
          "start" : 348,
          "length" : 4
        }
      ]
    },
    {
      "name" : "fsh-generated/resources/StructureDefinition-IHE.mCSD.Endpoint.DocShare.json",
      "size" : 3439,
      "processes" : [
        {
          "activity" : "load",
          "start" : 67,
          "length" : 16
        },
        {
          "activity" : "generateSnapshots",
          "start" : 70,
          "length" : 78
        },
        {
          "activity" : "generateNarratives",
          "start" : 76,
          "length" : 27
        },
        {
          "activity" : "validate",
          "start" : 85,
          "length" : 140
        },
        {
          "activity" : "checkConformanceResources",
          "start" : 93,
          "length" : 3
        },
        {
          "activity" : "scanForUsageStats",
          "start" : 109,
          "length" : 1
        },
        {
          "activity" : "validate",
          "start" : 115,
          "length" : 8
        },
        {
          "activity" : "generate1",
          "start" : 126,
          "length" : 231
        },
        {
          "activity" : "generate2",
          "start" : 160,
          "length" : 454
        },
        {
          "activity" : "generate2",
          "start" : 175,
          "length" : 112
        },
        {
          "activity" : "generateValidationPack",
          "start" : 303,
          "length" : 6
        },
        {
          "activity" : "scanExamplesForR5",
          "start" : 348,
          "length" : 1
        }
      ]
    },
    {
      "name" : "fsh-generated/resources/StructureDefinition-IHE.mCSD.Endpoint.json",
      "size" : 3596,
      "processes" : [
        {
          "activity" : "loadResources",
          "start" : 67,
          "length" : 16
        },
        {
          "activity" : "generateNarratives",
          "start" : 76,
          "length" : 23
        },
        {
          "activity" : "validate",
          "start" : 85,
          "length" : 110
        },
        {
          "activity" : "checkConformanceResources",
          "start" : 93,
          "length" : 1
        },
        {
          "activity" : "validate",
          "start" : 115,
          "length" : 2
        },
        {
          "activity" : "generate1",
          "start" : 127,
          "length" : 218
        },
        {
          "activity" : "generate2",
          "start" : 161,
          "length" : 378
        },
        {
          "activity" : "generate2",
          "start" : 176,
          "length" : 109
        },
        {
          "activity" : "makeDependencies",
          "start" : 195,
          "length" : 1
        },
        {
          "activity" : "generateValidationPack",
          "start" : 303,
          "length" : 6
        }
      ]
    },
    {
      "name" : "fsh-generated/resources/StructureDefinition-IHE.mCSD.FacilityLocation.json",
      "size" : 3129,
      "processes" : [
        {
          "activity" : "load",
          "start" : 67,
          "length" : 16
        },
        {
          "activity" : "generateSnapshots",
          "start" : 70,
          "length" : 47
        },
        {
          "activity" : "load-configure",
          "start" : 71,
          "length" : 15
        },
        {
          "activity" : "generateNarratives",
          "start" : 76,
          "length" : 42
        },
        {
          "activity" : "validate",
          "start" : 85,
          "length" : 203
        },
        {
          "activity" : "checkConformanceResources",
          "start" : 93,
          "length" : 5
        },
        {
          "activity" : "scanForUsageStats",
          "start" : 109,
          "length" : 1
        },
        {
          "activity" : "validate",
          "start" : 115,
          "length" : 6
        },
        {
          "activity" : "generate1",
          "start" : 127,
          "length" : 300
        },
        {
          "activity" : "generate2",
          "start" : 161,
          "length" : 535
        },
        {
          "activity" : "generate2",
          "start" : 176,
          "length" : 191
        },
        {
          "activity" : "generateExampleZip",
          "start" : 302,
          "length" : 1
        },
        {
          "activity" : "generateValidationPack",
          "start" : 303,
          "length" : 7
        }
      ]
    },
    {
      "name" : "fsh-generated/resources/StructureDefinition-IHE.mCSD.FacilityOrganization.json",
      "size" : 2304,
      "processes" : [
        {
          "activity" : "loadResources",
          "start" : 67,
          "length" : 15
        },
        {
          "activity" : "load",
          "start" : 67,
          "length" : 15
        },
        {
          "activity" : "generateSnapshots",
          "start" : 70,
          "length" : 15
        },
        {
          "activity" : "load-configure",
          "start" : 71,
          "length" : 32
        },
        {
          "activity" : "generateNarratives",
          "start" : 76,
          "length" : 22
        },
        {
          "activity" : "validate",
          "start" : 86,
          "length" : 141
        },
        {
          "activity" : "checkConformanceResources",
          "start" : 93,
          "length" : 1
        },
        {
          "activity" : "validate",
          "start" : 115,
          "length" : 6
        },
        {
          "activity" : "generate1",
          "start" : 127,
          "length" : 246
        },
        {
          "activity" : "generate2",
          "start" : 162,
          "length" : 516
        },
        {
          "activity" : "generate2",
          "start" : 176,
          "length" : 157
        },
        {
          "activity" : "generateExampleZip",
          "start" : 302,
          "length" : 1
        },
        {
          "activity" : "generateValidationPack",
          "start" : 303,
          "length" : 7
        },
        {
          "activity" : "scanExamplesForR5",
          "start" : 348,
          "length" : 1
        }
      ]
    },
    {
      "name" : "fsh-generated/resources/StructureDefinition-IHE.mCSD.HealthcareService.json",
      "size" : 2615,
      "processes" : [
        {
          "activity" : "load",
          "start" : 67,
          "length" : 16
        },
        {
          "activity" : "generateSnapshots",
          "start" : 70,
          "length" : 32
        },
        {
          "activity" : "generateNarratives",
          "start" : 76,
          "length" : 24
        },
        {
          "activity" : "validate",
          "start" : 86,
          "length" : 219
        },
        {
          "activity" : "checkConformanceResources",
          "start" : 93,
          "length" : 2
        },
        {
          "activity" : "scanForUsageStats",
          "start" : 109,
          "length" : 1
        },
        {
          "activity" : "validate",
          "start" : 115,
          "length" : 3
        },
        {
          "activity" : "generate1",
          "start" : 127,
          "length" : 330
        },
        {
          "activity" : "generate2",
          "start" : 162,
          "length" : 536
        },
        {
          "activity" : "generate2",
          "start" : 176,
          "length" : 247
        },
        {
          "activity" : "generateValidationPack",
          "start" : 303,
          "length" : 10
        }
      ]
    },
    {
      "name" : "fsh-generated/resources/StructureDefinition-IHE.mCSD.JurisdictionLocation.json",
      "size" : 4450,
      "processes" : [
        {
          "activity" : "loadResources",
          "start" : 67,
          "length" : 16
        },
        {
          "activity" : "load",
          "start" : 68,
          "length" : 16
        },
        {
          "activity" : "generateSnapshots",
          "start" : 70,
          "length" : 31
        },
        {
          "activity" : "load-configure",
          "start" : 71,
          "length" : 31
        },
        {
          "activity" : "generateNarratives",
          "start" : 76,
          "length" : 30
        },
        {
          "activity" : "validate",
          "start" : 86,
          "length" : 219
        },
        {
          "activity" : "checkConformanceResources",
          "start" : 93,
          "length" : 1
        },
        {
          "activity" : "scanForUsageStats",
          "start" : 109,
          "length" : 1
        },
        {
          "activity" : "validate",
          "start" : 115,
          "length" : 5
        },
        {
          "activity" : "generate1",
          "start" : 128,
          "length" : 390
        },
        {
          "activity" : "generate2",
          "start" : 163,
          "length" : 572
        },
        {
          "activity" : "generate2",
          "start" : 176,
          "length" : 274
        },
        {
          "activity" : "generateValidationPack",
          "start" : 303,
          "length" : 9
        },
        {
          "activity" : "scanExamplesForR5",
          "start" : 348,
          "length" : 1
        }
      ]
    },
    {
      "name" : "fsh-generated/resources/StructureDefinition-IHE.mCSD.JurisdictionOrganization.json",
      "size" : 2346,
      "processes" : [
        {
          "activity" : "load",
          "start" : 68,
          "length" : 15
        },
        {
          "activity" : "generateSnapshots",
          "start" : 70,
          "length" : 15
        },
        {
          "activity" : "load-configure",
          "start" : 71,
          "length" : 16
        },
        {
          "activity" : "generateNarratives",
          "start" : 76,
          "length" : 19
        },
        {
          "activity" : "validate",
          "start" : 86,
          "length" : 141
        },
        {
          "activity" : "checkConformanceResources",
          "start" : 93,
          "length" : 1
        },
        {
          "activity" : "validate",
          "start" : 115,
          "length" : 6
        },
        {
          "activity" : "generate1",
          "start" : 128,
          "length" : 251
        },
        {
          "activity" : "generate2",
          "start" : 163,
          "length" : 445
        },
        {
          "activity" : "generate2",
          "start" : 177,
          "length" : 139
        },
        {
          "activity" : "generateValidationPack",
          "start" : 303,
          "length" : 7
        }
      ]
    },
    {
      "name" : "fsh-generated/resources/StructureDefinition-IHE.mCSD.Location.json",
      "size" : 2729,
      "processes" : [
        {
          "activity" : "loadResources",
          "start" : 67,
          "length" : 15
        },
        {
          "activity" : "generateNarratives",
          "start" : 76,
          "length" : 20
        },
        {
          "activity" : "validate",
          "start" : 86,
          "length" : 203
        },
        {
          "activity" : "checkConformanceResources",
          "start" : 93,
          "length" : 2
        },
        {
          "activity" : "scanForUsageStats",
          "start" : 109,
          "length" : 1
        },
        {
          "activity" : "validate",
          "start" : 115,
          "length" : 3
        },
        {
          "activity" : "generate1",
          "start" : 128,
          "length" : 292
        },
        {
          "activity" : "generate2",
          "start" : 164,
          "length" : 473
        },
        {
          "activity" : "generate2",
          "start" : 177,
          "length" : 164
        },
        {
          "activity" : "generateValidationPack",
          "start" : 303,
          "length" : 5
        },
        {
          "activity" : "scanExamplesForR5",
          "start" : 348,
          "length" : 1
        }
      ]
    },
    {
      "name" : "fsh-generated/resources/StructureDefinition-IHE.mCSD.LocationDistance.json",
      "size" : 945,
      "processes" : [
        {
          "activity" : "load",
          "start" : 68,
          "length" : 16
        },
        {
          "activity" : "generateSnapshots",
          "start" : 70,
          "length" : 16
        },
        {
          "activity" : "generateNarratives",
          "start" : 76,
          "length" : 20
        },
        {
          "activity" : "validate",
          "start" : 87,
          "length" : 187
        },
        {
          "activity" : "checkConformanceResources",
          "start" : 93,
          "length" : 3
        },
        {
          "activity" : "scanForUsageStats",
          "start" : 109,
          "length" : 1
        },
        {
          "activity" : "validate",
          "start" : 115,
          "length" : 3
        },
        {
          "activity" : "generate1",
          "start" : 129,
          "length" : 239
        },
        {
          "activity" : "generate2",
          "start" : 164,
          "length" : 446
        },
        {
          "activity" : "generate2",
          "start" : 177,
          "length" : 161
        },
        {
          "activity" : "generateExampleZip",
          "start" : 301,
          "length" : 1
        },
        {
          "activity" : "generateValidationPack",
          "start" : 303,
          "length" : 5
        }
      ]
    },
    {
      "name" : "fsh-generated/resources/StructureDefinition-IHE.mCSD.Organization.json",
      "size" : 3348,
      "processes" : [
        {
          "activity" : "generateNarratives",
          "start" : 76,
          "length" : 24
        },
        {
          "activity" : "validate",
          "start" : 87,
          "length" : 125
        },
        {
          "activity" : "checkConformanceResources",
          "start" : 93,
          "length" : 1
        },
        {
          "activity" : "validate",
          "start" : 115,
          "length" : 5
        },
        {
          "activity" : "generate1",
          "start" : 129,
          "length" : 257
        },
        {
          "activity" : "generate2",
          "start" : 165,
          "length" : 402
        },
        {
          "activity" : "generate2",
          "start" : 177,
          "length" : 120
        },
        {
          "activity" : "generateValidationPack",
          "start" : 303,
          "length" : 6
        }
      ]
    },
    {
      "name" : "fsh-generated/resources/StructureDefinition-IHE.mCSD.OrganizationAffiliation.DocShare.json",
      "size" : 2874,
      "processes" : [
        {
          "activity" : "loadResources",
          "start" : 67,
          "length" : 16
        },
        {
          "activity" : "load",
          "start" : 68,
          "length" : 15
        },
        {
          "activity" : "generateSnapshots",
          "start" : 70,
          "length" : 47
        },
        {
          "activity" : "generateNarratives",
          "start" : 76,
          "length" : 20
        },
        {
          "activity" : "validate",
          "start" : 87,
          "length" : 125
        },
        {
          "activity" : "checkConformanceResources",
          "start" : 93,
          "length" : 5
        },
        {
          "activity" : "validate",
          "start" : 115,
          "length" : 7
        },
        {
          "activity" : "generate1",
          "start" : 129,
          "length" : 215
        },
        {
          "activity" : "generate2",
          "start" : 165,
          "length" : 452
        },
        {
          "activity" : "generate2",
          "start" : 177,
          "length" : 100
        },
        {
          "activity" : "generateValidationPack",
          "start" : 303,
          "length" : 4
        },
        {
          "activity" : "scanExamplesForR5",
          "start" : 348,
          "length" : 1
        }
      ]
    },
    {
      "name" : "fsh-generated/resources/StructureDefinition-IHE.mCSD.OrganizationAffiliation.json",
      "size" : 3788,
      "processes" : [
        {
          "activity" : "load",
          "start" : 68,
          "length" : 16
        },
        {
          "activity" : "generateNarratives",
          "start" : 76,
          "length" : 20
        },
        {
          "activity" : "validate",
          "start" : 87,
          "length" : 141
        },
        {
          "activity" : "checkConformanceResources",
          "start" : 93,
          "length" : 3
        },
        {
          "activity" : "scanForUsageStats",
          "start" : 109,
          "length" : 1
        },
        {
          "activity" : "validate",
          "start" : 115,
          "length" : 3
        },
        {
          "activity" : "generate1",
          "start" : 129,
          "length" : 248
        },
        {
          "activity" : "generate2",
          "start" : 165,
          "length" : 430
        },
        {
          "activity" : "generate2",
          "start" : 177,
          "length" : 95
        },
        {
          "activity" : "generateValidationPack",
          "start" : 303,
          "length" : 5
        },
        {
          "activity" : "scanExamplesForR5",
          "start" : 348,
          "length" : 1
        }
      ]
    },
    {
      "name" : "fsh-generated/resources/StructureDefinition-IHE.mCSD.Practitioner.json",
      "size" : 1774,
      "processes" : [
        {
          "activity" : "loadResources",
          "start" : 67,
          "length" : 16
        },
        {
          "activity" : "load",
          "start" : 68,
          "length" : 16
        },
        {
          "activity" : "load-configure",
          "start" : 71,
          "length" : 15
        },
        {
          "activity" : "generateNarratives",
          "start" : 76,
          "length" : 16
        },
        {
          "activity" : "validate",
          "start" : 87,
          "length" : 140
        },
        {
          "activity" : "checkConformanceResources",
          "start" : 93,
          "length" : 1
        },
        {
          "activity" : "validate",
          "start" : 115,
          "length" : 5
        },
        {
          "activity" : "generate1",
          "start" : 130,
          "length" : 207
        },
        {
          "activity" : "generate2",
          "start" : 166,
          "length" : 477
        },
        {
          "activity" : "generate2",
          "start" : 177,
          "length" : 124
        },
        {
          "activity" : "generateValidationPack",
          "start" : 303,
          "length" : 4
        },
        {
          "activity" : "scanExamplesForR5",
          "start" : 348,
          "length" : 2
        }
      ]
    },
    {
      "name" : "fsh-generated/resources/StructureDefinition-IHE.mCSD.PractitionerRole.json",
      "size" : 3444,
      "processes" : [
        {
          "activity" : "generateSnapshots",
          "start" : 70,
          "length" : 16
        },
        {
          "activity" : "load-configure",
          "start" : 71,
          "length" : 31
        },
        {
          "activity" : "generateNarratives",
          "start" : 76,
          "length" : 23
        },
        {
          "activity" : "validate",
          "start" : 87,
          "length" : 157
        },
        {
          "activity" : "checkConformanceResources",
          "start" : 93,
          "length" : 1
        },
        {
          "activity" : "scanForUsageStats",
          "start" : 109,
          "length" : 1
        },
        {
          "activity" : "validate",
          "start" : 115,
          "length" : 6
        },
        {
          "activity" : "generate1",
          "start" : 130,
          "length" : 276
        },
        {
          "activity" : "generate2",
          "start" : 166,
          "length" : 556
        },
        {
          "activity" : "generate2",
          "start" : 177,
          "length" : 144
        },
        {
          "activity" : "generateValidationPack",
          "start" : 303,
          "length" : 50
        }
      ]
    },
    {
      "name" : "fsh-generated/resources/StructureDefinition-IHE.mCSD.PurposeOfUse.json",
      "size" : 1568,
      "processes" : [
        {
          "activity" : "loadResources",
          "start" : 67,
          "length" : 15
        },
        {
          "activity" : "load",
          "start" : 68,
          "length" : 15
        },
        {
          "activity" : "generateSnapshots",
          "start" : 70,
          "length" : 15
        },
        {
          "activity" : "generateNarratives",
          "start" : 76,
          "length" : 46
        },
        {
          "activity" : "validate",
          "start" : 87,
          "length" : 47
        },
        {
          "activity" : "checkConformanceResources",
          "start" : 93,
          "length" : 2
        },
        {
          "activity" : "validate",
          "start" : 115,
          "length" : 4
        },
        {
          "activity" : "generate1",
          "start" : 130,
          "length" : 96
        },
        {
          "activity" : "generate2",
          "start" : 167,
          "length" : 294
        },
        {
          "activity" : "generate2",
          "start" : 178,
          "length" : 40
        },
        {
          "activity" : "generateValidationPack",
          "start" : 303,
          "length" : 5
        }
      ]
    },
    {
      "name" : "fsh-generated/resources/StructureDefinition-ihe-endpointspecifictype.json",
      "size" : 1991,
      "processes" : [
        {
          "activity" : "load",
          "start" : 68,
          "length" : 16
        },
        {
          "activity" : "generateSnapshots",
          "start" : 70,
          "length" : 16
        },
        {
          "activity" : "generateNarratives",
          "start" : 76,
          "length" : 12
        },
        {
          "activity" : "validate",
          "start" : 87,
          "length" : 31
        },
        {
          "activity" : "checkConformanceResources",
          "start" : 93,
          "length" : 2
        },
        {
          "activity" : "validate",
          "start" : 115,
          "length" : 3
        },
        {
          "activity" : "generate1",
          "start" : 130,
          "length" : 102
        },
        {
          "activity" : "generate2",
          "start" : 167,
          "length" : 276
        },
        {
          "activity" : "generate2",
          "start" : 178,
          "length" : 41
        },
        {
          "activity" : "generateValidationPack",
          "start" : 303,
          "length" : 2
        }
      ]
    },
    {
      "name" : "fsh-generated/resources/ValueSet-IHE.mCSD.Organization.Location.Types.json",
      "size" : 572,
      "processes" : [
        {
          "activity" : "loadResources",
          "start" : 67,
          "length" : 16
        },
        {
          "activity" : "generateNarratives",
          "start" : 76,
          "length" : 100
        },
        {
          "activity" : "validate",
          "start" : 77,
          "length" : 16
        },
        {
          "activity" : "validate",
          "start" : 115,
          "length" : 5
        },
        {
          "activity" : "generate1",
          "start" : 130,
          "length" : 33
        },
        {
          "activity" : "generate2",
          "start" : 168,
          "length" : 160
        },
        {
          "activity" : "generateExampleZip",
          "start" : 302,
          "length" : 1
        },
        {
          "activity" : "generateValidationPack",
          "start" : 303,
          "length" : 2
        }
      ]
    },
    {
      "name" : "fsh-generated/resources/ValueSet-MCSDEndpointIdentifierTypeValueSet.json",
      "size" : 564,
      "processes" : [
        {
          "activity" : "load",
          "start" : 67,
          "length" : 16
        },
        {
          "activity" : "generateNarratives",
          "start" : 76,
          "length" : 8
        },
        {
          "activity" : "validate",
          "start" : 77,
          "length" : 15
        },
        {
          "activity" : "validate",
          "start" : 115,
          "length" : 7
        },
        {
          "activity" : "generate1",
          "start" : 130,
          "length" : 34
        },
        {
          "activity" : "generate2",
          "start" : 168,
          "length" : 157
        },
        {
          "activity" : "generateExampleZip",
          "start" : 301,
          "length" : 1
        },
        {
          "activity" : "generateValidationPack",
          "start" : 303,
          "length" : 1
        }
      ]
    },
    {
      "name" : "fsh-generated/resources/ValueSet-MCSDEndpointTypesCoreDocShareVS.json",
      "size" : 960,
      "processes" : [
        {
          "activity" : "generateNarratives",
          "start" : 76,
          "length" : 23
        },
        {
          "activity" : "validate",
          "start" : 77,
          "length" : 16
        },
        {
          "activity" : "validate",
          "start" : 115,
          "length" : 3
        },
        {
          "activity" : "generate1",
          "start" : 130,
          "length" : 36
        },
        {
          "activity" : "generate2",
          "start" : 168,
          "length" : 222
        },
        {
          "activity" : "generateValidationPack",
          "start" : 303,
          "length" : 1
        }
      ]
    },
    {
      "name" : "fsh-generated/resources/ValueSet-MCSDEndpointTypesVS.json",
      "size" : 463,
      "processes" : [
        {
          "activity" : "loadResources",
          "start" : 67,
          "length" : 16
        },
        {
          "activity" : "load",
          "start" : 67,
          "length" : 15
        },
        {
          "activity" : "generateNarratives",
          "start" : 76,
          "length" : 9
        },
        {
          "activity" : "validate",
          "start" : 77,
          "length" : 16
        },
        {
          "activity" : "validate",
          "start" : 115,
          "length" : 5
        },
        {
          "activity" : "generate1",
          "start" : 130,
          "length" : 31
        },
        {
          "activity" : "generate2",
          "start" : 168,
          "length" : 363
        }
      ]
    },
    {
      "name" : "fsh-generated/resources/ValueSet-MCSDOrgAffTypesVS.json",
      "size" : 558,
      "processes" : [
        {
          "activity" : "load",
          "start" : 67,
          "length" : 16
        },
        {
          "activity" : "generateNarratives",
          "start" : 76,
          "length" : 9
        },
        {
          "activity" : "validate",
          "start" : 77,
          "length" : 31
        },
        {
          "activity" : "validate",
          "start" : 115,
          "length" : 6
        },
        {
          "activity" : "generate1",
          "start" : 130,
          "length" : 32
        },
        {
          "activity" : "generate2",
          "start" : 168,
          "length" : 154
        },
        {
          "activity" : "generateExampleZip",
          "start" : 302,
          "length" : 1
        },
        {
          "activity" : "generateValidationPack",
          "start" : 303,
          "length" : 1
        }
      ]
    },
    {
      "name" : "fsh-generated/resources/ValueSet-MCSDOrganizationIdentifierTypeValueSet.json",
      "size" : 588,
      "processes" : [
        {
          "activity" : "generateNarratives",
          "start" : 76,
          "length" : 9
        },
        {
          "activity" : "validate",
          "start" : 115,
          "length" : 3
        },
        {
          "activity" : "generate1",
          "start" : 130,
          "length" : 34
        },
        {
          "activity" : "generate2",
          "start" : 169,
          "length" : 157
        }
      ]
    }
  ]
}
