{
  "date" : "Thu, 12 Dec, 2024 08:26:08 -0600",
  "doco" : "For each file: start is seconds after start activity occurred. Length = milliseconds activity took",
  "files" : [
    {
      "name" : "\\fsh-generated\\resources\\ImplementationGuide-ihe.iti.scheduling.json",
      "size" : 19168,
      "processes" : [
        {
          "activity" : "load",
          "start" : 380,
          "length" : 16
        },
        {
          "activity" : "checkR4R4B",
          "start" : 381,
          "length" : 4
        },
        {
          "activity" : "generateNarratives",
          "start" : 381,
          "length" : 250
        },
        {
          "activity" : "validate",
          "start" : 395,
          "length" : 1764
        },
        {
          "activity" : "scanForUsageStats",
          "start" : 411,
          "length" : 1
        },
        {
          "activity" : "validate",
          "start" : 412,
          "length" : 4
        },
        {
          "activity" : "generate1",
          "start" : 412,
          "length" : 239
        },
        {
          "activity" : "generate2",
          "start" : 425,
          "length" : 156
        },
        {
          "activity" : "generateValidationPack",
          "start" : 552,
          "length" : 5
        },
        {
          "activity" : "scanExamplesForR5",
          "start" : 585,
          "length" : 1
        }
      ]
    },
    {
      "name" : "fsh-generated/resources/AuditEvent-ex-auditSchedulingBook-recipient.json",
      "size" : 2712,
      "processes" : [
        {
          "activity" : "loadResources",
          "start" : 379,
          "length" : 7
        },
        {
          "activity" : "generateNarratives",
          "start" : 381,
          "length" : 842
        },
        {
          "activity" : "validate",
          "start" : 412,
          "length" : 160
        },
        {
          "activity" : "generate1",
          "start" : 413,
          "length" : 56
        },
        {
          "activity" : "generate2",
          "start" : 426,
          "length" : 64
        },
        {
          "activity" : "generateExampleZip",
          "start" : 552,
          "length" : 1
        }
      ]
    },
    {
      "name" : "fsh-generated/resources/AuditEvent-ex-auditSchedulingBook-source.json",
      "size" : 2740,
      "processes" : [
        {
          "activity" : "loadResources",
          "start" : 379,
          "length" : 7
        },
        {
          "activity" : "load-configure",
          "start" : 379,
          "length" : 1
        },
        {
          "activity" : "generateNarratives",
          "start" : 382,
          "length" : 7
        },
        {
          "activity" : "validate",
          "start" : 412,
          "length" : 35
        },
        {
          "activity" : "generate1",
          "start" : 413,
          "length" : 50
        },
        {
          "activity" : "generate2",
          "start" : 426,
          "length" : 76
        }
      ]
    },
    {
      "name" : "fsh-generated/resources/AuditEvent-ex-auditSchedulingFindPotential-recipient.json",
      "size" : 2741,
      "processes" : [
        {
          "activity" : "loadResources",
          "start" : 379,
          "length" : 7
        },
        {
          "activity" : "generateNarratives",
          "start" : 382,
          "length" : 11
        },
        {
          "activity" : "validate",
          "start" : 412,
          "length" : 43
        },
        {
          "activity" : "generate1",
          "start" : 413,
          "length" : 46
        },
        {
          "activity" : "generate2",
          "start" : 426,
          "length" : 77
        }
      ]
    },
    {
      "name" : "fsh-generated/resources/AuditEvent-ex-auditSchedulingFindPotential-source.json",
      "size" : 2769,
      "processes" : [
        {
          "activity" : "loadResources",
          "start" : 379,
          "length" : 6
        },
        {
          "activity" : "load-configure",
          "start" : 379,
          "length" : 1
        },
        {
          "activity" : "checkR4R4B",
          "start" : 381,
          "length" : 2
        },
        {
          "activity" : "generateNarratives",
          "start" : 382,
          "length" : 10
        },
        {
          "activity" : "scanForUsageStats",
          "start" : 411,
          "length" : 1
        },
        {
          "activity" : "validate",
          "start" : 412,
          "length" : 38
        },
        {
          "activity" : "generate1",
          "start" : 413,
          "length" : 49
        },
        {
          "activity" : "generate2",
          "start" : 426,
          "length" : 51
        }
      ]
    },
    {
      "name" : "fsh-generated/resources/AuditEvent-ex-auditSchedulingHold-recipient.json",
      "size" : 2712,
      "processes" : [
        {
          "activity" : "loadResources",
          "start" : 379,
          "length" : 6
        },
        {
          "activity" : "checkR4R4B",
          "start" : 381,
          "length" : 1
        },
        {
          "activity" : "generateNarratives",
          "start" : 382,
          "length" : 10
        },
        {
          "activity" : "validate",
          "start" : 412,
          "length" : 35
        },
        {
          "activity" : "generate1",
          "start" : 413,
          "length" : 43
        },
        {
          "activity" : "generate2",
          "start" : 426,
          "length" : 41
        }
      ]
    },
    {
      "name" : "fsh-generated/resources/AuditEvent-ex-auditSchedulingHold-source.json",
      "size" : 2740,
      "processes" : [
        {
          "activity" : "loadResources",
          "start" : 379,
          "length" : 5
        },
        {
          "activity" : "generateNarratives",
          "start" : 382,
          "length" : 7
        },
        {
          "activity" : "validate",
          "start" : 412,
          "length" : 37
        },
        {
          "activity" : "generate1",
          "start" : 413,
          "length" : 42
        },
        {
          "activity" : "generate2",
          "start" : 426,
          "length" : 43
        },
        {
          "activity" : "generateExampleZip",
          "start" : 552,
          "length" : 1
        }
      ]
    },
    {
      "name" : "fsh-generated/resources/CapabilityStatement-IHE.Scheduling.client.json",
      "size" : 8718,
      "processes" : [
        {
          "activity" : "loadResources",
          "start" : 379,
          "length" : 6
        },
        {
          "activity" : "load-configure",
          "start" : 379,
          "length" : 1
        },
        {
          "activity" : "load",
          "start" : 380,
          "length" : 9
        },
        {
          "activity" : "generateNarratives",
          "start" : 382,
          "length" : 35
        },
        {
          "activity" : "validate",
          "start" : 395,
          "length" : 118
        },
        {
          "activity" : "validate",
          "start" : 412,
          "length" : 3
        },
        {
          "activity" : "generate1",
          "start" : 413,
          "length" : 80
        },
        {
          "activity" : "generate2",
          "start" : 426,
          "length" : 48
        },
        {
          "activity" : "generateValidationPack",
          "start" : 552,
          "length" : 2
        }
      ]
    },
    {
      "name" : "fsh-generated/resources/CapabilityStatement-IHE.Scheduling.server.json",
      "size" : 8968,
      "processes" : [
        {
          "activity" : "loadResources",
          "start" : 379,
          "length" : 7
        },
        {
          "activity" : "load",
          "start" : 380,
          "length" : 10
        },
        {
          "activity" : "generateNarratives",
          "start" : 382,
          "length" : 27
        },
        {
          "activity" : "validate",
          "start" : 395,
          "length" : 65
        },
        {
          "activity" : "validate",
          "start" : 412,
          "length" : 2
        },
        {
          "activity" : "generate1",
          "start" : 413,
          "length" : 84
        },
        {
          "activity" : "generate2",
          "start" : 426,
          "length" : 79
        },
        {
          "activity" : "generateValidationPack",
          "start" : 552,
          "length" : 1
        }
      ]
    },
    {
      "name" : "fsh-generated/resources/Device-ex-device.json",
      "size" : 205,
      "processes" : [
        {
          "activity" : "loadResources",
          "start" : 379,
          "length" : 6
        },
        {
          "activity" : "scan",
          "start" : 379,
          "length" : 1
        },
        {
          "activity" : "generateNarratives",
          "start" : 382,
          "length" : 2
        },
        {
          "activity" : "validate",
          "start" : 412,
          "length" : 6
        },
        {
          "activity" : "generate1",
          "start" : 413,
          "length" : 27
        },
        {
          "activity" : "generate2",
          "start" : 426,
          "length" : 36
        }
      ]
    },
    {
      "name" : "fsh-generated/resources/StructureDefinition-IHE.Scheduling.Book.Audit.Recipient.json",
      "size" : 2917,
      "processes" : [
        {
          "activity" : "loadResources",
          "start" : 379,
          "length" : 6
        },
        {
          "activity" : "load-configure",
          "start" : 379,
          "length" : 1
        },
        {
          "activity" : "load",
          "start" : 380,
          "length" : 9
        },
        {
          "activity" : "generateSnapshots",
          "start" : 380,
          "length" : 158
        },
        {
          "activity" : "checkR4R4B",
          "start" : 381,
          "length" : 1
        },
        {
          "activity" : "generateNarratives",
          "start" : 382,
          "length" : 86
        },
        {
          "activity" : "validate",
          "start" : 383,
          "length" : 2309
        },
        {
          "activity" : "checkConformanceResources",
          "start" : 397,
          "length" : 3
        },
        {
          "activity" : "scanForUsageStats",
          "start" : 411,
          "length" : 19
        },
        {
          "activity" : "validate",
          "start" : 412,
          "length" : 3
        },
        {
          "activity" : "generate1",
          "start" : 413,
          "length" : 1081
        },
        {
          "activity" : "generate2",
          "start" : 426,
          "length" : 4580
        },
        {
          "activity" : "generateValidationPack",
          "start" : 552,
          "length" : 22
        },
        {
          "activity" : "scanExamplesForR5",
          "start" : 585,
          "length" : 1
        }
      ]
    },
    {
      "name" : "fsh-generated/resources/StructureDefinition-IHE.Scheduling.Book.Audit.Source.json",
      "size" : 2902,
      "processes" : [
        {
          "activity" : "loadResources",
          "start" : 379,
          "length" : 6
        },
        {
          "activity" : "load",
          "start" : 380,
          "length" : 9
        },
        {
          "activity" : "generateSnapshots",
          "start" : 380,
          "length" : 157
        },
        {
          "activity" : "generateNarratives",
          "start" : 382,
          "length" : 55
        },
        {
          "activity" : "validate",
          "start" : 385,
          "length" : 1757
        },
        {
          "activity" : "checkConformanceResources",
          "start" : 397,
          "length" : 3
        },
        {
          "activity" : "scanForUsageStats",
          "start" : 411,
          "length" : 6
        },
        {
          "activity" : "validate",
          "start" : 412,
          "length" : 6
        },
        {
          "activity" : "generate1",
          "start" : 414,
          "length" : 1096
        },
        {
          "activity" : "generate2",
          "start" : 431,
          "length" : 2563
        },
        {
          "activity" : "generateValidationPack",
          "start" : 552,
          "length" : 25
        },
        {
          "activity" : "scanProfilesForR5",
          "start" : 585,
          "length" : 1
        },
        {
          "activity" : "scanExamplesForR5",
          "start" : 585,
          "length" : 1
        }
      ]
    },
    {
      "name" : "fsh-generated/resources/StructureDefinition-IHE.Scheduling.FindPotential.Audit.Recipient.json",
      "size" : 2534,
      "processes" : [
        {
          "activity" : "loadResources",
          "start" : 379,
          "length" : 6
        },
        {
          "activity" : "load",
          "start" : 380,
          "length" : 8
        },
        {
          "activity" : "generateSnapshots",
          "start" : 380,
          "length" : 140
        },
        {
          "activity" : "generateNarratives",
          "start" : 382,
          "length" : 49
        },
        {
          "activity" : "validate",
          "start" : 387,
          "length" : 1638
        },
        {
          "activity" : "checkConformanceResources",
          "start" : 397,
          "length" : 3
        },
        {
          "activity" : "scanForUsageStats",
          "start" : 411,
          "length" : 18
        },
        {
          "activity" : "validate",
          "start" : 412,
          "length" : 3
        },
        {
          "activity" : "generate1",
          "start" : 415,
          "length" : 1136
        },
        {
          "activity" : "generate2",
          "start" : 433,
          "length" : 2440
        },
        {
          "activity" : "generateValidationPack",
          "start" : 552,
          "length" : 24
        },
        {
          "activity" : "scanExamplesForR5",
          "start" : 585,
          "length" : 1
        }
      ]
    },
    {
      "name" : "fsh-generated/resources/StructureDefinition-IHE.Scheduling.FindPotential.Audit.Source.json",
      "size" : 2971,
      "processes" : [
        {
          "activity" : "loadResources",
          "start" : 379,
          "length" : 6
        },
        {
          "activity" : "load",
          "start" : 380,
          "length" : 8
        },
        {
          "activity" : "generateSnapshots",
          "start" : 380,
          "length" : 149
        },
        {
          "activity" : "generateNarratives",
          "start" : 382,
          "length" : 50
        },
        {
          "activity" : "validate",
          "start" : 389,
          "length" : 3210
        },
        {
          "activity" : "checkConformanceResources",
          "start" : 397,
          "length" : 4
        },
        {
          "activity" : "generateLogicalMaps",
          "start" : 411,
          "length" : 1
        },
        {
          "activity" : "scanForUsageStats",
          "start" : 411,
          "length" : 6
        },
        {
          "activity" : "validate",
          "start" : 412,
          "length" : 4
        },
        {
          "activity" : "generate1",
          "start" : 416,
          "length" : 1062
        },
        {
          "activity" : "generate2",
          "start" : 436,
          "length" : 2201
        },
        {
          "activity" : "generateExampleZip",
          "start" : 551,
          "length" : 1
        },
        {
          "activity" : "generateValidationPack",
          "start" : 553,
          "length" : 19
        },
        {
          "activity" : "scanExamplesForR5",
          "start" : 585,
          "length" : 2
        }
      ]
    },
    {
      "name" : "fsh-generated/resources/StructureDefinition-IHE.Scheduling.Hold.Audit.Recipient.json",
      "size" : 2917,
      "processes" : [
        {
          "activity" : "loadResources",
          "start" : 379,
          "length" : 6
        },
        {
          "activity" : "load-configure",
          "start" : 379,
          "length" : 1
        },
        {
          "activity" : "load",
          "start" : 380,
          "length" : 14
        },
        {
          "activity" : "generateSnapshots",
          "start" : 380,
          "length" : 160
        },
        {
          "activity" : "generateNarratives",
          "start" : 382,
          "length" : 53
        },
        {
          "activity" : "validate",
          "start" : 392,
          "length" : 1124
        },
        {
          "activity" : "checkConformanceResources",
          "start" : 397,
          "length" : 3
        },
        {
          "activity" : "scanForUsageStats",
          "start" : 411,
          "length" : 15
        },
        {
          "activity" : "validate",
          "start" : 412,
          "length" : 7
        },
        {
          "activity" : "generate1",
          "start" : 417,
          "length" : 1056
        },
        {
          "activity" : "generate2",
          "start" : 438,
          "length" : 2401
        },
        {
          "activity" : "generateValidationPack",
          "start" : 553,
          "length" : 19
        },
        {
          "activity" : "scanProfilesForR5",
          "start" : 585,
          "length" : 1
        },
        {
          "activity" : "scanExamplesForR5",
          "start" : 585,
          "length" : 1
        }
      ]
    },
    {
      "name" : "fsh-generated/resources/StructureDefinition-IHE.Scheduling.Hold.Audit.Source.json",
      "size" : 2902,
      "processes" : [
        {
          "activity" : "loadResources",
          "start" : 379,
          "length" : 7
        },
        {
          "activity" : "load",
          "start" : 380,
          "length" : 9
        },
        {
          "activity" : "generateSnapshots",
          "start" : 381,
          "length" : 143
        },
        {
          "activity" : "generateNarratives",
          "start" : 382,
          "length" : 49
        },
        {
          "activity" : "validate",
          "start" : 393,
          "length" : 919
        },
        {
          "activity" : "checkConformanceResources",
          "start" : 397,
          "length" : 3
        },
        {
          "activity" : "scanForUsageStats",
          "start" : 411,
          "length" : 6
        },
        {
          "activity" : "validate",
          "start" : 412,
          "length" : 3
        },
        {
          "activity" : "generate1",
          "start" : 419,
          "length" : 1078
        },
        {
          "activity" : "generate2",
          "start" : 440,
          "length" : 11843
        },
        {
          "activity" : "generateValidationPack",
          "start" : 553,
          "length" : 20
        },
        {
          "activity" : "scanExamplesForR5",
          "start" : 585,
          "length" : 1
        }
      ]
    },
    {
      "name" : "input/examples/example-appointment.json",
      "size" : 1518,
      "processes" : [
        {
          "activity" : "loadResources",
          "start" : 379,
          "length" : 6
        },
        {
          "activity" : "load",
          "start" : 380,
          "length" : 1
        },
        {
          "activity" : "generateNarratives",
          "start" : 382,
          "length" : 13
        },
        {
          "activity" : "validate",
          "start" : 412,
          "length" : 16
        },
        {
          "activity" : "generate1",
          "start" : 420,
          "length" : 42
        },
        {
          "activity" : "generate2",
          "start" : 452,
          "length" : 61
        }
      ]
    },
    {
      "name" : "input/examples/example-iti-scheduling-bundle.json",
      "size" : 10031,
      "processes" : [
        {
          "activity" : "loadResources",
          "start" : 379,
          "length" : 8
        },
        {
          "activity" : "load",
          "start" : 380,
          "length" : 9
        },
        {
          "activity" : "generateNarratives",
          "start" : 382,
          "length" : 12
        },
        {
          "activity" : "validate",
          "start" : 412,
          "length" : 48
        },
        {
          "activity" : "generate1",
          "start" : 420,
          "length" : 299
        },
        {
          "activity" : "generate2",
          "start" : 452,
          "length" : 67
        }
      ]
    },
    {
      "name" : "input/examples/example-patient.json",
      "size" : 1777,
      "processes" : [
        {
          "activity" : "loadResources",
          "start" : 379,
          "length" : 6
        },
        {
          "activity" : "generateNarratives",
          "start" : 382,
          "length" : 21
        },
        {
          "activity" : "validate",
          "start" : 412,
          "length" : 32
        },
        {
          "activity" : "generate1",
          "start" : 420,
          "length" : 285
        },
        {
          "activity" : "generate2",
          "start" : 452,
          "length" : 70
        }
      ]
    },
    {
      "name" : "input/examples/example-practitioner.json",
      "size" : 652,
      "processes" : [
        {
          "activity" : "loadResources",
          "start" : 379,
          "length" : 6
        },
        {
          "activity" : "load-configure",
          "start" : 379,
          "length" : 1
        },
        {
          "activity" : "generateNarratives",
          "start" : 382,
          "length" : 7
        },
        {
          "activity" : "validate",
          "start" : 412,
          "length" : 12
        },
        {
          "activity" : "generate1",
          "start" : 420,
          "length" : 27
        },
        {
          "activity" : "generate2",
          "start" : 452,
          "length" : 69
        }
      ]
    },
    {
      "name" : "input/resources/StructureDefinition-iti-sched-appt.xml",
      "size" : 5085,
      "processes" : [
        {
          "activity" : "loadResources",
          "start" : 379,
          "length" : 27
        },
        {
          "activity" : "load",
          "start" : 380,
          "length" : 11
        },
        {
          "activity" : "generateSnapshots",
          "start" : 381,
          "length" : 40
        },
        {
          "activity" : "generateNarratives",
          "start" : 382,
          "length" : 34
        },
        {
          "activity" : "validate",
          "start" : 394,
          "length" : 244
        },
        {
          "activity" : "checkConformanceResources",
          "start" : 397,
          "length" : 1
        },
        {
          "activity" : "scanForUsageStats",
          "start" : 411,
          "length" : 2
        },
        {
          "activity" : "validate",
          "start" : 412,
          "length" : 5
        },
        {
          "activity" : "generate1",
          "start" : 420,
          "length" : 317
        },
        {
          "activity" : "generate2",
          "start" : 452,
          "length" : 1658
        },
        {
          "activity" : "makeDependencies",
          "start" : 484,
          "length" : 1
        },
        {
          "activity" : "generateValidationPack",
          "start" : 553,
          "length" : 7
        },
        {
          "activity" : "scanExamplesForR5",
          "start" : 585,
          "length" : 1
        }
      ]
    },
    {
      "name" : "input/resources/StructureDefinition-iti-sched-bundle.xml",
      "size" : 3928,
      "processes" : [
        {
          "activity" : "loadResources",
          "start" : 379,
          "length" : 25
        },
        {
          "activity" : "load",
          "start" : 380,
          "length" : 11
        },
        {
          "activity" : "generateSnapshots",
          "start" : 381,
          "length" : 79
        },
        {
          "activity" : "generateNarratives",
          "start" : 382,
          "length" : 32
        },
        {
          "activity" : "validate",
          "start" : 394,
          "length" : 481
        },
        {
          "activity" : "checkConformanceResources",
          "start" : 397,
          "length" : 3
        },
        {
          "activity" : "scanForUsageStats",
          "start" : 412,
          "length" : 2
        },
        {
          "activity" : "validate",
          "start" : 412,
          "length" : 6
        },
        {
          "activity" : "generate1",
          "start" : 421,
          "length" : 607
        },
        {
          "activity" : "generate2",
          "start" : 454,
          "length" : 1379
        },
        {
          "activity" : "generateExampleZip",
          "start" : 552,
          "length" : 1
        },
        {
          "activity" : "generateValidationPack",
          "start" : 553,
          "length" : 9
        }
      ]
    },
    {
      "name" : "input/resources/StructureDefinition-iti-sched-extension-status-reason.xml",
      "size" : 2604,
      "processes" : [
        {
          "activity" : "loadResources",
          "start" : 379,
          "length" : 19
        },
        {
          "activity" : "load",
          "start" : 380,
          "length" : 10
        },
        {
          "activity" : "generateSnapshots",
          "start" : 381,
          "length" : 9
        },
        {
          "activity" : "generateNarratives",
          "start" : 383,
          "length" : 13
        },
        {
          "activity" : "validate",
          "start" : 395,
          "length" : 64
        },
        {
          "activity" : "checkConformanceResources",
          "start" : 397,
          "length" : 5
        },
        {
          "activity" : "validate",
          "start" : 412,
          "length" : 9
        },
        {
          "activity" : "generate1",
          "start" : 421,
          "length" : 92
        },
        {
          "activity" : "generate2",
          "start" : 455,
          "length" : 271
        },
        {
          "activity" : "generateValidationPack",
          "start" : 553,
          "length" : 2
        }
      ]
    },
    {
      "name" : "input/resources/codesystem-status-reason.xml",
      "size" : 8020,
      "processes" : [
        {
          "activity" : "loadResources",
          "start" : 379,
          "length" : 26
        },
        {
          "activity" : "load",
          "start" : 380,
          "length" : 13
        },
        {
          "activity" : "checkR4R4B",
          "start" : 381,
          "length" : 1
        },
        {
          "activity" : "generateNarratives",
          "start" : 383,
          "length" : 18
        },
        {
          "activity" : "validate",
          "start" : 383,
          "length" : 55
        },
        {
          "activity" : "checkConformanceResources",
          "start" : 397,
          "length" : 1
        },
        {
          "activity" : "scanForUsageStats",
          "start" : 412,
          "length" : 1
        },
        {
          "activity" : "validate",
          "start" : 412,
          "length" : 2
        },
        {
          "activity" : "generate1",
          "start" : 421,
          "length" : 80
        },
        {
          "activity" : "generate2",
          "start" : 456,
          "length" : 3188
        },
        {
          "activity" : "generateValidationPack",
          "start" : 553,
          "length" : 2
        }
      ]
    },
    {
      "name" : "input/resources/operationdefinition-appointment-book.xml",
      "size" : 5635,
      "processes" : [
        {
          "activity" : "loadResources",
          "start" : 379,
          "length" : 27
        },
        {
          "activity" : "load-configure",
          "start" : 379,
          "length" : 15
        },
        {
          "activity" : "load",
          "start" : 380,
          "length" : 9
        },
        {
          "activity" : "generateNarratives",
          "start" : 383,
          "length" : 13
        },
        {
          "activity" : "validate",
          "start" : 395,
          "length" : 32
        },
        {
          "activity" : "validate",
          "start" : 397,
          "length" : 1
        },
        {
          "activity" : "validate",
          "start" : 412,
          "length" : 6
        },
        {
          "activity" : "generate1",
          "start" : 421,
          "length" : 57
        },
        {
          "activity" : "generate2",
          "start" : 459,
          "length" : 42
        },
        {
          "activity" : "generateValidationPack",
          "start" : 553,
          "length" : 1
        }
      ]
    },
    {
      "name" : "input/resources/operationdefinition-appointment-find.xml",
      "size" : 13442,
      "processes" : [
        {
          "activity" : "loadResources",
          "start" : 379,
          "length" : 46
        },
        {
          "activity" : "load",
          "start" : 380,
          "length" : 12
        },
        {
          "activity" : "generateNarratives",
          "start" : 383,
          "length" : 26
        },
        {
          "activity" : "validate",
          "start" : 395,
          "length" : 38
        },
        {
          "activity" : "validate",
          "start" : 412,
          "length" : 6
        },
        {
          "activity" : "generate1",
          "start" : 421,
          "length" : 110
        },
        {
          "activity" : "generate2",
          "start" : 459,
          "length" : 47
        },
        {
          "activity" : "generateValidationPack",
          "start" : 553,
          "length" : 2
        }
      ]
    },
    {
      "name" : "input/resources/operationdefinition-appointment-hold.xml",
      "size" : 2787,
      "processes" : [
        {
          "activity" : "loadResources",
          "start" : 379,
          "length" : 18
        },
        {
          "activity" : "load-configure",
          "start" : 379,
          "length" : 1
        },
        {
          "activity" : "load",
          "start" : 380,
          "length" : 8
        },
        {
          "activity" : "generateNarratives",
          "start" : 383,
          "length" : 11
        },
        {
          "activity" : "validate",
          "start" : 395,
          "length" : 14
        },
        {
          "activity" : "validate",
          "start" : 412,
          "length" : 2
        },
        {
          "activity" : "generate1",
          "start" : 422,
          "length" : 42
        },
        {
          "activity" : "generate2",
          "start" : 459,
          "length" : 39
        },
        {
          "activity" : "generateExampleZip",
          "start" : 552,
          "length" : 1
        }
      ]
    },
    {
      "name" : "input/resources/valueset-sct-services.xml",
      "size" : 2714,
      "processes" : [
        {
          "activity" : "loadResources",
          "start" : 379,
          "length" : 17
        },
        {
          "activity" : "scan",
          "start" : 379,
          "length" : 1
        },
        {
          "activity" : "load",
          "start" : 380,
          "length" : 13
        },
        {
          "activity" : "load",
          "start" : 380,
          "length" : 1
        },
        {
          "activity" : "checkR4R4B",
          "start" : 381,
          "length" : 1
        },
        {
          "activity" : "generateNarratives",
          "start" : 383,
          "length" : 115
        },
        {
          "activity" : "validate",
          "start" : 383,
          "length" : 29
        },
        {
          "activity" : "validate",
          "start" : 412,
          "length" : 10
        },
        {
          "activity" : "generate1",
          "start" : 422,
          "length" : 48
        },
        {
          "activity" : "generate2",
          "start" : 459,
          "length" : 12510
        },
        {
          "activity" : "generateValidationPack",
          "start" : 553,
          "length" : 1
        }
      ]
    },
    {
      "name" : "input/resources/valueset-specialty.xml",
      "size" : 1067,
      "processes" : [
        {
          "activity" : "loadResources",
          "start" : 379,
          "length" : 14
        },
        {
          "activity" : "load",
          "start" : 380,
          "length" : 9
        },
        {
          "activity" : "generateNarratives",
          "start" : 383,
          "length" : 10
        },
        {
          "activity" : "validate",
          "start" : 383,
          "length" : 26
        },
        {
          "activity" : "validate",
          "start" : 412,
          "length" : 2
        },
        {
          "activity" : "generate1",
          "start" : 422,
          "length" : 33
        },
        {
          "activity" : "generate2",
          "start" : 472,
          "length" : 1207
        }
      ]
    },
    {
      "name" : "input/resources/valueset-status-reason.xml",
      "size" : 694,
      "processes" : [
        {
          "activity" : "loadResources",
          "start" : 379,
          "length" : 15
        },
        {
          "activity" : "load-configure",
          "start" : 379,
          "length" : 1
        },
        {
          "activity" : "load",
          "start" : 380,
          "length" : 8
        },
        {
          "activity" : "generateNarratives",
          "start" : 383,
          "length" : 12
        },
        {
          "activity" : "validate",
          "start" : 383,
          "length" : 14
        },
        {
          "activity" : "validate",
          "start" : 412,
          "length" : 3
        },
        {
          "activity" : "generate1",
          "start" : 422,
          "length" : 32
        },
        {
          "activity" : "generate2",
          "start" : 473,
          "length" : 251
        },
        {
          "activity" : "generateValidationPack",
          "start" : 553,
          "length" : 1
        }
      ]
    }
  ]
}
