{
  "date" : "Wed, 14 Feb, 2024 09:37:16 -0600",
  "doco" : "For each file: start is seconds after start activity occurred. Length = milliseconds activity took",
  "files" : [
    {
      "name" : "\\input\\implementationguide-IHE.FormatCode.xml",
      "size" : 4143,
      "processes" : [
        {
          "activity" : "load",
          "start" : 28,
          "length" : 183
        },
        {
          "activity" : "checkR4R4B",
          "start" : 28,
          "length" : 24
        },
        {
          "activity" : "validate",
          "start" : 30,
          "length" : 1133
        },
        {
          "activity" : "checkConformanceResources2",
          "start" : 32,
          "length" : 1
        },
        {
          "activity" : "scanForUsageStats",
          "start" : 36,
          "length" : 1
        },
        {
          "activity" : "generate1",
          "start" : 37,
          "length" : 208
        },
        {
          "activity" : "generate2",
          "start" : 40,
          "length" : 227
        },
        {
          "activity" : "generateExampleZip",
          "start" : 77,
          "length" : 1
        },
        {
          "activity" : "generateValidationPack",
          "start" : 77,
          "length" : 3
        },
        {
          "activity" : "scanExamplesForR5",
          "start" : 82,
          "length" : 3
        }
      ]
    },
    {
      "name" : "input/resources/Bundle-history-IHE-formatcode.codesystem.xml",
      "size" : 15547,
      "processes" : [
        {
          "activity" : "loadResources",
          "start" : 27,
          "length" : 259
        },
        {
          "activity" : "load-configure",
          "start" : 28,
          "length" : 1
        },
        {
          "activity" : "loadInfo",
          "start" : 28,
          "length" : 1
        },
        {
          "activity" : "load",
          "start" : 28,
          "length" : 78
        },
        {
          "activity" : "load",
          "start" : 28,
          "length" : 1
        },
        {
          "activity" : "load",
          "start" : 28,
          "length" : 1
        },
        {
          "activity" : "checkR4R4B",
          "start" : 28,
          "length" : 5
        },
        {
          "activity" : "generateNarratives",
          "start" : 28,
          "length" : 541
        },
        {
          "activity" : "validate",
          "start" : 36,
          "length" : 533
        },
        {
          "activity" : "processProvenanceDetails",
          "start" : 37,
          "length" : 15
        },
        {
          "activity" : "generate1",
          "start" : 38,
          "length" : 228
        },
        {
          "activity" : "generate2",
          "start" : 41,
          "length" : 157
        }
      ]
    },
    {
      "name" : "input/resources/Bundle-history-IHE-formatcode.valueset.xml",
      "size" : 4791,
      "processes" : [
        {
          "activity" : "loadResources",
          "start" : 27,
          "length" : 62
        },
        {
          "activity" : "load",
          "start" : 28,
          "length" : 21
        },
        {
          "activity" : "checkR4R4B",
          "start" : 28,
          "length" : 1
        },
        {
          "activity" : "generateNarratives",
          "start" : 29,
          "length" : 53
        },
        {
          "activity" : "validate",
          "start" : 37,
          "length" : 58
        },
        {
          "activity" : "processProvenanceDetails",
          "start" : 37,
          "length" : 7
        },
        {
          "activity" : "generate1",
          "start" : 38,
          "length" : 86
        },
        {
          "activity" : "generate2",
          "start" : 41,
          "length" : 132
        }
      ]
    },
    {
      "name" : "input/resources/codesystem-formatcode.xml",
      "size" : 49316,
      "processes" : [
        {
          "activity" : "loadResources",
          "start" : 27,
          "length" : 267
        },
        {
          "activity" : "load",
          "start" : 28,
          "length" : 182
        },
        {
          "activity" : "checkR4R4B",
          "start" : 28,
          "length" : 9
        },
        {
          "activity" : "generateNarratives",
          "start" : 29,
          "length" : 142
        },
        {
          "activity" : "validate",
          "start" : 29,
          "length" : 1268
        },
        {
          "activity" : "checkConformanceResources",
          "start" : 32,
          "length" : 1
        },
        {
          "activity" : "scanForUsageStats",
          "start" : 36,
          "length" : 1
        },
        {
          "activity" : "generate1",
          "start" : 38,
          "length" : 318
        },
        {
          "activity" : "generate2",
          "start" : 41,
          "length" : 2947
        },
        {
          "activity" : "generateValidationPack",
          "start" : 77,
          "length" : 6
        },
        {
          "activity" : "scanExamplesForR5",
          "start" : 82,
          "length" : 3
        }
      ]
    },
    {
      "name" : "input/resources/valueset-formatcode.xml",
      "size" : 2166,
      "processes" : [
        {
          "activity" : "loadResources",
          "start" : 28,
          "length" : 21
        },
        {
          "activity" : "load-configure",
          "start" : 28,
          "length" : 1
        },
        {
          "activity" : "load",
          "start" : 28,
          "length" : 47
        },
        {
          "activity" : "generateNarratives",
          "start" : 29,
          "length" : 187
        },
        {
          "activity" : "validate",
          "start" : 30,
          "length" : 66
        },
        {
          "activity" : "checkURLsUnique",
          "start" : 36,
          "length" : 1
        },
        {
          "activity" : "generate1",
          "start" : 38,
          "length" : 30
        },
        {
          "activity" : "generate2",
          "start" : 44,
          "length" : 6419
        },
        {
          "activity" : "makeDependencies",
          "start" : 57,
          "length" : 1
        },
        {
          "activity" : "generateValidationPack",
          "start" : 77,
          "length" : 1
        }
      ]
    }
  ]
}
