{
  "resourceType" : "DocumentReference",
  "id" : "ex-consent-ink",
  "text" : {
    "status" : "generated",
    "div" : "<div xmlns=\"http://www.w3.org/1999/xhtml\"><p><b>Generated Narrative: DocumentReference</b><a name=\"ex-consent-ink\"> </a></p><div style=\"display: inline-block; background-color: #d9e0e7; padding: 6px; margin: 4px; border: 1px solid #8da1b4; border-radius: 5px; line-height: 60%\"><p style=\"margin-bottom: 0px\">Resource DocumentReference &quot;ex-consent-ink&quot; </p></div><p><b>status</b>: current</p><blockquote><p><b>content</b></p><h3>Attachments</h3><table class=\"grid\"><tr><td>-</td><td><b>ContentType</b></td><td><b>Url</b></td></tr><tr><td>*</td><td>image/png</td><td><code>Binary/B-ink</code></td></tr></table></blockquote></div>"
  },
  "status" : "current",
  "content" : [{
    "attachment" : {
      "contentType" : "image/png",
      "url" : "Binary/B-ink"
    }
  }]
}