{
  "resourceType" : "ValueSet",
  "id" : "6fb6721d-c75f-48bd-af61-c8843746ed18-8",
  "url" : "http://hl7.org/fhir/comparison/ValueSet/6fb6721d-c75f-48bd-af61-c8843746ed18-8",
  "name" : "UnionCommonTagsAndCommonTags",
  "title" : "Union of Common Tags And Common Tags",
  "status" : "draft",
  "date" : "2025-10-31T15:08:21-05:00",
  "jurisdiction" : [{
    "coding" : [{
      "system" : "http://unstats.un.org/unsd/methods/m49/m49.htm",
      "code" : "001",
      "display" : "World"
    }]
  }],
  "compose" : {
    "include" : [{
      
    },
    {
      "system" : "http://terminology.hl7.org/CodeSystem/v3-ObservationValue",
      "concept" : [{
        "code" : "SUBSETTED",
        "display" : "subsetted"
      }]
    }]
  }
}