<?xml version="1.0" encoding="UTF-8"?><Bundle xmlns="http://hl7.org/fhir"><type value="collection"/><entry/><entry><resource><OperationOutcome><extension url="http://hl7.org/fhir/StructureDefinition/operationoutcome-file"><valueString value="C:\Users\johnm\temp\ihe.iti.sips#1.0.0-milestone\fsh-generated\resources\CapabilityStatement-IHE.sIPS.ContentConsumer"/></extension></OperationOutcome></resource></entry><entry><resource><OperationOutcome><extension url="http://hl7.org/fhir/StructureDefinition/operationoutcome-file"><valueString value="C:\Users\johnm\temp\ihe.iti.sips#1.0.0-milestone\fsh-generated\resources\CapabilityStatement-IHE.sIPS.ContentCreator"/></extension></OperationOutcome></resource></entry><entry><resource><OperationOutcome><extension url="http://hl7.org/fhir/StructureDefinition/operationoutcome-file"><valueString value="C:\Users\johnm\temp\ihe.iti.sips#1.0.0-milestone\fsh-generated\resources\DocumentReference-ex-DocumentReference-Bundle-01-json"/></extension></OperationOutcome></resource></entry><entry><resource><OperationOutcome><extension url="http://hl7.org/fhir/StructureDefinition/operationoutcome-file"><valueString value="C:\Users\johnm\temp\ihe.iti.sips#1.0.0-milestone\fsh-generated\resources\DocumentReference-ex-DocumentReference-Bundle-01-xml"/></extension></OperationOutcome></resource></entry><entry><resource><OperationOutcome><extension url="http://hl7.org/fhir/StructureDefinition/operationoutcome-file"><valueString value="C:\Users\johnm\temp\ihe.iti.sips#1.0.0-milestone\fsh-generated\resources\ImplementationGuide-ihe.iti.sips"/></extension></OperationOutcome></resource></entry><entry><resource><OperationOutcome><extension url="http://hl7.org/fhir/StructureDefinition/operationoutcome-file"><valueString value="C:\Users\johnm\temp\ihe.iti.sips#1.0.0-milestone\fsh-generated\resources\Organization-890751f4-2924-4636-bab7-efffc7f3cf15"/></extension></OperationOutcome></resource></entry><entry><resource><OperationOutcome><extension url="http://hl7.org/fhir/StructureDefinition/operationoutcome-file"><valueString value="C:\Users\johnm\temp\ihe.iti.sips#1.0.0-milestone\fsh-generated\resources\Patient-2b90dd2b-2dab-4c75-9bb9-a355e07401e8"/></extension></OperationOutcome></resource></entry><entry><resource><OperationOutcome><extension url="http://hl7.org/fhir/StructureDefinition/operationoutcome-file"><valueString value="C:\Users\johnm\temp\ihe.iti.sips#1.0.0-milestone\fsh-generated\resources\Practitioner-1c616b24-3895-48c4-9a02-9a64110351ef"/></extension></OperationOutcome></resource></entry></Bundle>