{
  "resourceType": "ValueSet",
  "id": "imr-servicerequest-intent-vs",
  "text": {
    "status": "extensions",
    "div": "<div xmlns=\"http://www.w3.org/1999/xhtml\"><ul><li>Include these codes as defined in <a href=\"http://hl7.org/fhir/R4/codesystem-request-intent.html\"><code>http://hl7.org/fhir/request-intent</code></a><table class=\"none\"><tr><td style=\"white-space:nowrap\"><b>Code</b></td><td><b>Display</b></td><td><b>Definition</b></td></tr><tr><td><a href=\"http://hl7.org/fhir/R4/codesystem-request-intent.html#request-intent-order\">order</a></td><td>Order</td><td>The request represents a request/demand and authorization for action by a Practitioner.</td></tr><tr><td><a href=\"http://hl7.org/fhir/R4/codesystem-request-intent.html#request-intent-original-order\">original-order</a></td><td>Original Order</td><td>The request represents an original authorization for action.</td></tr><tr><td><a href=\"http://hl7.org/fhir/R4/codesystem-request-intent.html#request-intent-reflex-order\">reflex-order</a></td><td>Reflex Order</td><td>The request represents an automatically generated supplemental authorization for action based on a parent authorization together with initial results of the action taken against that parent authorization.</td></tr><tr><td><a href=\"http://hl7.org/fhir/R4/codesystem-request-intent.html#request-intent-filler-order\">filler-order</a></td><td>Filler Order</td><td>The request represents the view of an authorization instantiated by a fulfilling system representing the details of the fulfiller's intention to act upon a submitted order.</td></tr><tr><td><a href=\"http://hl7.org/fhir/R4/codesystem-request-intent.html#request-intent-instance-order\">instance-order</a></td><td>Instance Order</td><td>An order created in fulfillment of a broader order that represents the authorization for a single activity occurrence.  E.g. The administration of a single dose of a drug.</td></tr></table></li></ul></div>"
  },
  "url": "https://profiles.ihe.net/RAD/IMR/ValueSet/imr-servicerequest-intent-vs",
  "version": "1.0.0",
  "name": "IMRServiceRequestIntentVS",
  "title": "IMR ServiceRequest intent Value Set",
  "status": "active",
  "date": "2022-07-25T14:40:04-05:00",
  "publisher": "IHE Radiology Technical Committee",
  "contact": [
    {
      "telecom": [
        {
          "system": "url",
          "value": "https://www.ihe.net/ihe_domains/radiology/"
        }
      ]
    },
    {
      "telecom": [
        {
          "system": "email",
          "value": "radiology@ihe.net"
        }
      ]
    },
    {
      "name": "IHE Radiology Technical Committee",
      "telecom": [
        {
          "system": "email",
          "value": "radiology@ihe.net"
        }
      ]
    }
  ],
  "description": "Codes representing the applicable intent for a ServiceRequestd.",
  "jurisdiction": [
    {
      "coding": [
        {
          "system": "http://unstats.un.org/unsd/methods/m49/m49.htm",
          "code": "001"
        }
      ]
    }
  ],
  "compose": {
    "include": [
      {
        "system": "http://hl7.org/fhir/request-intent",
        "concept": [
          {
            "code": "order",
            "display": "Order"
          },
          {
            "code": "original-order",
            "display": "Original Order"
          },
          {
            "code": "reflex-order",
            "display": "Reflex Order"
          },
          {
            "code": "filler-order",
            "display": "Filler Order"
          },
          {
            "code": "instance-order",
            "display": "Instance Order"
          }
        ]
      }
    ]
  }
}