{
  "list" : [
    {
      "version" : "current",
      "path" : "https://build.fhir.org/ig/IHE/PCC.ODH/branches/master/index.html",
      "status" : "ci-build",
      "sequence" : "ci-build"
    },
    {
      "version" : "1.0.0",
      "path" : "https://profiles.ihe.net/PCC/ODH/1.0.0",
      "status" : "trial-use",
      "sequence" : "Publication",
      "fhirversion" : "4.0.1",
      "date" : "2024-12-04",
      "current" : true,
      "desc" : "Trial Implementation - resolved public-comment"
    },
    {
      "version" : "1.0.0-comment",
      "path" : "https://profiles.ihe.net/PCC/ODH/1.0.0-comment",
      "status" : "ballot",
      "sequence" : "Publication",
      "fhirversion" : "4.0.1",
      "date" : "2024-03-08",
      "desc" : "Public-Comment"
    }
  ],
  "package-id" : "ihe.pcc.odh",
  "canonical" : "https://profiles.ihe.net/PCC/ODH",
  "title" : "IHE FHIR Profile: Occupational Data for Health (ODH) - International",
  "category" : "Clinical Records",
  "introduction" : "This IG covers the specific data that covers past or present jobs, usual work, employment status, retirement date and combat zone period for the subject. It also includes the past or present jobs and usual work of other household members. This IG is International scope."
}
