{
  "resourceType" : "ValueSet",
  "id" : "DSUBmPublishBundleActions",
  "text" : {
    "status" : "extensions",
    "div" : "<div xmlns=\"http://www.w3.org/1999/xhtml\"><ul><li>Include these codes as defined in <a href=\"http://hl7.org/fhir/R4B/codesystem-http-verb.html\"><code>http://hl7.org/fhir/http-verb</code></a><table class=\"none\"><tr><td style=\"white-space:nowrap\"><b>Code</b></td><td><b>Display</b></td><td><b>Definition</b></td></tr><tr><td><a href=\"http://hl7.org/fhir/R4B/codesystem-http-verb.html#http-verb-POST\">POST</a></td><td style=\"color: #cccccc\">POST</td><td>HTTP POST Command.</td></tr><tr><td><a href=\"http://hl7.org/fhir/R4B/codesystem-http-verb.html#http-verb-PUT\">PUT</a></td><td style=\"color: #cccccc\">PUT</td><td>HTTP PUT Command.</td></tr><tr><td><a href=\"http://hl7.org/fhir/R4B/codesystem-http-verb.html#http-verb-DELETE\">DELETE</a></td><td style=\"color: #cccccc\">DELETE</td><td>HTTP DELETE Command.</td></tr></table></li></ul></div>"
  },
  "url" : "https://profiles.ihe.net/ITI/DSUBm/ValueSet/DSUBmPublishBundleActions",
  "version" : "1.0.0-comment",
  "name" : "DSUBmPublishBundleActions",
  "title" : "DSUBm Update to document sharing resources actions ValueSet",
  "status" : "active",
  "experimental" : false,
  "date" : "2023-11-17T09:35:47-06:00",
  "publisher" : "IHE IT Infrastructure Technical Committee",
  "contact" : [{
    "telecom" : [{
      "system" : "url",
      "value" : "https://www.ihe.net/ihe_domains/it_infrastructure/"
    }]
  },
  {
    "telecom" : [{
      "system" : "email",
      "value" : "iti@ihe.net"
    }]
  },
  {
    "name" : "IHE IT Infrastructure Technical Committee",
    "telecom" : [{
      "system" : "email",
      "value" : "iti@ihe.net"
    }]
  }],
  "description" : "A ValueSet of the allowed actions in a ITI-111 Resource Publish for the Folder List type and the DocumentReference resources.",
  "jurisdiction" : [{
    "coding" : [{
      "system" : "http://unstats.un.org/unsd/methods/m49/m49.htm",
      "code" : "001"
    }]
  }],
  "compose" : {
    "include" : [{
      "system" : "http://hl7.org/fhir/http-verb",
      "concept" : [{
        "code" : "POST"
      },
      {
        "code" : "PUT"
      },
      {
        "code" : "DELETE"
      }]
    }]
  }
}